<?xml version="1.0" encoding="UTF-8"?>
<files>
  <file name="01.あの日のままのぼくら.mp3" source="original">
    <mtime>1738340110</mtime>
    <size>9854053</size>
    <md5>efa0cb72181840a5c6e947f3daf4944d</md5>
    <crc32>31b0a032</crc32>
    <sha1>a17adb9e100219b0878a97166f77a7c56fe3f9dd</sha1>
    <format>VBR MP3</format>
    <length>191.26</length>
    <title>あの日のままのぼくら</title>
    <creator>アクア(CV:雨宮天)、めぐみん(CV:高橋李依)、ダクネス(CV:茅野愛衣)</creator>
    <album>TVアニメ『この素晴らしい世界に祝福を！3』エンディング・テーマ「あの日のままのぼくら」</album>
    <track>1/5</track>
    <artist>アクア(CV:雨宮天)、めぐみん(CV:高橋李依)、ダクネス(CV:茅野愛衣)</artist>
    <genre>JPOP</genre>
    <comment>https://www.yumeost.net</comment>
  </file>
  <file name="01.あの日のままのぼくら.png" source="derivative">
    <format>PNG</format>
    <original>01.あの日のままのぼくら.mp3</original>
    <mtime>1738340290</mtime>
    <size>44403</size>
    <md5>cf3f666609755459e206da2b98583a04</md5>
    <crc32>eb067d23</crc32>
    <sha1>2fb6931807d5a651ff3729fd40aeaf72f5c05c60</sha1>
  </file>
  <file name="01.あの日のままのぼくら_spectrogram.png" source="derivative">
    <format>Spectrogram</format>
    <original>01.あの日のままのぼくら.mp3</original>
    <mtime>1738340666</mtime>
    <size>294096</size>
    <md5>ad1386c8183956805c73c83da7e2c350</md5>
    <crc32>3a48d59f</crc32>
    <sha1>d5cbcccac8d41e2edafc0bee838a2562958e4de2</sha1>
  </file>
  <file name="02.あの日のままのぼくら -アクア ver.-.mp3" source="original">
    <mtime>1738340137</mtime>
    <size>9854075</size>
    <md5>9fd6475984c1259d294f0f61eb1fd392</md5>
    <crc32>e215e4a6</crc32>
    <sha1>35437b6c852019fdf5a33c7656e866fc5beda4c4</sha1>
    <format>VBR MP3</format>
    <length>191.26</length>
    <title>あの日のままのぼくら -アクア ver.-</title>
    <creator>アクア(CV:雨宮天)、めぐみん(CV:高橋李依)、ダクネス(CV:茅野愛衣)</creator>
    <album>TVアニメ『この素晴らしい世界に祝福を！3』エンディング・テーマ「あの日のままのぼくら」</album>
    <track>2/5</track>
    <artist>アクア(CV:雨宮天)、めぐみん(CV:高橋李依)、ダクネス(CV:茅野愛衣)</artist>
    <genre>JPOP</genre>
    <comment>https://www.yumeost.net</comment>
  </file>
  <file name="02.あの日のままのぼくら -アクア ver.-.png" source="derivative">
    <format>PNG</format>
    <original>02.あの日のままのぼくら -アクア ver.-.mp3</original>
    <mtime>1738340393</mtime>
    <size>44143</size>
    <md5>9f31d685bf6b8868b0b103926388589d</md5>
    <crc32>474a7c1c</crc32>
    <sha1>3a1d0c6e38843ea06bc5b454d412248ad1dd9c7a</sha1>
  </file>
  <file name="02.あの日のままのぼくら -アクア ver.-_spectrogram.png" source="derivative">
    <format>Spectrogram</format>
    <original>02.あの日のままのぼくら -アクア ver.-.mp3</original>
    <mtime>1738340680</mtime>
    <size>290465</size>
    <md5>19a49eab2811972ca0e930b9cdce1117</md5>
    <crc32>cbb28dbe</crc32>
    <sha1>1c3595149ed4fb1832b1c43caa7b5fa2ac962ee6</sha1>
  </file>
  <file name="03.あの日のままのぼくら -めぐみん ver.-.mp3" source="original">
    <mtime>1738340123</mtime>
    <size>9854077</size>
    <md5>4695232d09cc23c5ee14d2e7998dba06</md5>
    <crc32>553052ce</crc32>
    <sha1>ad0594f0ac6d672bf2479236fa12df4f397de95d</sha1>
    <format>VBR MP3</format>
    <length>191.26</length>
    <title>あの日のままのぼくら -めぐみん ver.-</title>
    <creator>アクア(CV:雨宮天)、めぐみん(CV:高橋李依)、ダクネス(CV:茅野愛衣)</creator>
    <album>TVアニメ『この素晴らしい世界に祝福を！3』エンディング・テーマ「あの日のままのぼくら」</album>
    <track>3/5</track>
    <artist>アクア(CV:雨宮天)、めぐみん(CV:高橋李依)、ダクネス(CV:茅野愛衣)</artist>
    <genre>JPOP</genre>
    <comment>https://www.yumeost.net</comment>
  </file>
  <file name="03.あの日のままのぼくら -めぐみん ver.-.png" source="derivative">
    <format>PNG</format>
    <original>03.あの日のままのぼくら -めぐみん ver.-.mp3</original>
    <mtime>1738340452</mtime>
    <size>44529</size>
    <md5>a4e2875232ea232b5d186eb5c15a7dc0</md5>
    <crc32>0d40436e</crc32>
    <sha1>b6bcc3fb33a803fa9aae88ae4028d267ce7721d6</sha1>
  </file>
  <file name="03.あの日のままのぼくら -めぐみん ver.-_spectrogram.png" source="derivative">
    <format>Spectrogram</format>
    <original>03.あの日のままのぼくら -めぐみん ver.-.mp3</original>
    <mtime>1738340693</mtime>
    <size>296204</size>
    <md5>f658a90f4dd35f815536a738992e608f</md5>
    <crc32>df77ce5e</crc32>
    <sha1>19eaf0653fc8778957a47a73ecfe645b5db5868f</sha1>
  </file>
  <file name="04.あの日のままのぼくら -ダクネス ver.-.mp3" source="original">
    <mtime>1738340117</mtime>
    <size>9854077</size>
    <md5>e6c5a7517d4b7d831e1a7979eaf65fa9</md5>
    <crc32>631b659b</crc32>
    <sha1>cd9fb46a8be152abac42aa840bced2db563e09cb</sha1>
    <format>VBR MP3</format>
    <length>191.26</length>
    <title>あの日のままのぼくら -ダクネス ver.-</title>
    <creator>アクア(CV:雨宮天)、めぐみん(CV:高橋李依)、ダクネス(CV:茅野愛衣)</creator>
    <album>TVアニメ『この素晴らしい世界に祝福を！3』エンディング・テーマ「あの日のままのぼくら」</album>
    <track>4/5</track>
    <artist>アクア(CV:雨宮天)、めぐみん(CV:高橋李依)、ダクネス(CV:茅野愛衣)</artist>
    <genre>JPOP</genre>
    <comment>https://www.yumeost.net</comment>
  </file>
  <file name="04.あの日のままのぼくら -ダクネス ver.-.png" source="derivative">
    <format>PNG</format>
    <original>04.あの日のままのぼくら -ダクネス ver.-.mp3</original>
    <mtime>1738340490</mtime>
    <size>43994</size>
    <md5>447c51c9e6949062273188ae848d5676</md5>
    <crc32>d9e68e7a</crc32>
    <sha1>c6377f27dc7460f7778dc2ce444826cd67d6b34d</sha1>
  </file>
  <file name="04.あの日のままのぼくら -ダクネス ver.-_spectrogram.png" source="derivative">
    <format>Spectrogram</format>
    <original>04.あの日のままのぼくら -ダクネス ver.-.mp3</original>
    <mtime>1738340707</mtime>
    <size>290060</size>
    <md5>f1fbb4fc5fc75fe8997d9d7a15d81a84</md5>
    <crc32>f8115a44</crc32>
    <sha1>8d68e5ef777ac695ab5d17ea4bd17f1d81d46cdd</sha1>
  </file>
  <file name="05.あの日のままのぼくら (off vocal ver.).mp3" source="original">
    <mtime>1738340129</mtime>
    <size>9854087</size>
    <md5>5b871bb309be2a1dae5f789dea841ab5</md5>
    <crc32>d808d1c2</crc32>
    <sha1>4e6c1fff083f63f0aa7a362b580b5ad3cb86acbb</sha1>
    <format>VBR MP3</format>
    <length>191.26</length>
    <title>あの日のままのぼくら (off vocal ver.)</title>
    <creator>アクア(CV:雨宮天)、めぐみん(CV:高橋李依)、ダクネス(CV:茅野愛衣)</creator>
    <album>TVアニメ『この素晴らしい世界に祝福を！3』エンディング・テーマ「あの日のままのぼくら」</album>
    <track>5/5</track>
    <artist>アクア(CV:雨宮天)、めぐみん(CV:高橋李依)、ダクネス(CV:茅野愛衣)</artist>
    <genre>JPOP</genre>
    <comment>https://www.yumeost.net</comment>
  </file>
  <file name="05.あの日のままのぼくら (off vocal ver.).png" source="derivative">
    <format>PNG</format>
    <original>05.あの日のままのぼくら (off vocal ver.).mp3</original>
    <mtime>1738340649</mtime>
    <size>44700</size>
    <md5>7534a00a70c8e9b4fe01c7c2856df8f8</md5>
    <crc32>bf5e15c4</crc32>
    <sha1>2b85cb8c09a3d4e693208a770b3bc130fad6db77</sha1>
  </file>
  <file name="05.あの日のままのぼくら (off vocal ver.)_spectrogram.png" source="derivative">
    <format>Spectrogram</format>
    <original>05.あの日のままのぼくら (off vocal ver.).mp3</original>
    <mtime>1738340720</mtime>
    <size>284269</size>
    <md5>cfc67e67b5a25eff432b774633a02544</md5>
    <crc32>fd65d3f8</crc32>
    <sha1>b9d71e13bb0aec576f53ead967eba6d09b55c8e5</sha1>
  </file>
  <file name="__ia_thumb.jpg" source="original">
    <mtime>1738340179</mtime>
    <size>17511</size>
    <md5>579dabad42a5ca456f803a1286968101</md5>
    <crc32>8747aac3</crc32>
    <sha1>d30936a00566f538ede983cf7a0c78f248a290c4</sha1>
    <format>Item Tile</format>
  </file>
  <file name="cover.jpg" source="original">
    <mtime>1738340086</mtime>
    <size>248925</size>
    <md5>3881f8284f0f48a51eca54189d1afbe7</md5>
    <crc32>d88277de</crc32>
    <sha1>13f8d614f845208294052a855153866b7f0ec8f7</sha1>
    <format>JPEG</format>
  </file>
  <file name="cover_thumb.jpg" source="derivative">
    <format>JPEG Thumb</format>
    <original>cover.jpg</original>
    <mtime>1738340260</mtime>
    <size>11313</size>
    <md5>45d2c4a675f3ed683d3f2b6e9333b921</md5>
    <crc32>528cda41</crc32>
    <sha1>fec8cb1e5b3b5461c1630bfb48a7e281535a9d73</sha1>
  </file>
  <file name="konosuba-ending-song_archive.torrent" source="metadata">
    <btih>55bd3476ee6690041949f2b3ea0cba7a4b6bdc5e</btih>
    <mtime>1738340741</mtime>
    <size>7218</size>
    <md5>77081990b91559f356af413f21f37f78</md5>
    <crc32>aa2806c7</crc32>
    <sha1>7c22cb7efd36942d6995b299bcfbaae637ecd716</sha1>
    <format>Archive BitTorrent</format>
  </file>
  <file name="konosuba-ending-song_files.xml" source="original">
    <format>Metadata</format>
    <md5>d5e31a4f309dadc5aaeaf990316137a1</md5>
    <summation>md5</summation>
  </file>
  <file name="konosuba-ending-song_meta.sqlite" source="original">
    <mtime>1738340141</mtime>
    <size>32768</size>
    <md5>0d23648f3e016dcd0303a00879e9df3d</md5>
    <crc32>e61e4eab</crc32>
    <sha1>1c0a1f588d0ace7f7322618ec9ef998f53d85757</sha1>
    <format>Metadata</format>
  </file>
  <file name="konosuba-ending-song_meta.xml" source="original">
    <mtime>1738340732</mtime>
    <size>788</size>
    <md5>a9a7f11a5c3af18e298d13f580decd9a</md5>
    <crc32>be2a743f</crc32>
    <sha1>8c1fd74b44af06620150b132ec46e1321edc1dd0</sha1>
    <format>Metadata</format>
  </file>
</files>
