<?xml version="1.0" encoding="UTF-8"?>
<files>
  <file name="01 - Star Trek Voyager Main Title.afpk" source="derivative">
    <format>Columbia Peaks</format>
    <original>01 - Star Trek Voyager Main Title.mp3</original>
    <mtime>1593568783</mtime>
    <size>24208</size>
    <md5>97447c2747f7b940f2c1f6728bf24979</md5>
    <crc32>32af5d1c</crc32>
    <sha1>bb02eb0fe662df100448fdd7cf54ea13c2439ecb</sha1>
  </file>
  <file name="01 - Star Trek Voyager Main Title.mp3" source="original">
    <mtime>1593565474</mtime>
    <size>4695778</size>
    <md5>94bb40eb050ec7eeb4e1e05130ed82ae</md5>
    <crc32>3be726f7</crc32>
    <sha1>110cb58dd88b2b64431884fc1d4c09b6c47c3fff</sha1>
    <format>VBR MP3</format>
    <length>117.05</length>
    <height>200</height>
    <width>200</width>
    <title>Star Trek: Voyager Main Title</title>
    <creator>Jerry Goldsmith</creator>
    <album>Star Trek: Voyager Collection Vol. 1 - Disco 1</album>
    <track>01</track>
    <artist>Jerry Goldsmith</artist>
    <genre>Soundtrack</genre>
  </file>
  <file name="01 - Star Trek Voyager Main Title.png" source="derivative">
    <format>PNG</format>
    <original>01 - Star Trek Voyager Main Title.mp3</original>
    <mtime>1593568340</mtime>
    <size>27477</size>
    <md5>bf1cff11a71d464ca92e0e4819d4f275</md5>
    <crc32>63b04b9a</crc32>
    <sha1>082e20a9d306c3675764aff6bebc691942ab926d</sha1>
  </file>
  <file name="01 - Star Trek Voyager Main Title_spectrogram.png" source="derivative">
    <format>Spectrogram</format>
    <original>01 - Star Trek Voyager Main Title.mp3</original>
    <mtime>1593568543</mtime>
    <size>291730</size>
    <md5>505b04f0272ccabe38654244c476ecad</md5>
    <crc32>8065b8a4</crc32>
    <sha1>48c95539e170939727a4fa6c092da54cd24f87d3</sha1>
  </file>
  <file name="02 - Asteroid A' Comin'  [Rise].afpk" source="derivative">
    <format>Columbia Peaks</format>
    <original>02 - Asteroid A' Comin'  [Rise].mp3</original>
    <mtime>1593568698</mtime>
    <size>16864</size>
    <md5>a091169fe8cd571a2aadec20b51fd543</md5>
    <crc32>0520889b</crc32>
    <sha1>cc64ff030316e15a661ded8b398bbdb59fe172a7</sha1>
  </file>
  <file name="02 - Asteroid A' Comin'  [Rise].mp3" source="original">
    <mtime>1593565557</mtime>
    <size>3339491</size>
    <md5>d24182a6f9e8489566b7019f3aeca535</md5>
    <crc32>7085b98e</crc32>
    <sha1>2aed7ab268d7fd007c9489506f7faf6ad918f232</sha1>
    <format>VBR MP3</format>
    <length>83.15</length>
    <height>200</height>
    <width>200</width>
    <title>Asteroid A' Comin' [Rise]</title>
    <creator>Jay Chattaway</creator>
    <album>Star Trek: Voyager Collection Vol. 1 - Disco 1</album>
    <track>02</track>
    <artist>Jay Chattaway</artist>
    <genre>Soundtrack</genre>
  </file>
  <file name="02 - Asteroid A' Comin'  [Rise].png" source="derivative">
    <format>PNG</format>
    <original>02 - Asteroid A' Comin'  [Rise].mp3</original>
    <mtime>1593568396</mtime>
    <size>22383</size>
    <md5>0c35f028819572f5011091f9f19ea88d</md5>
    <crc32>e4b436d6</crc32>
    <sha1>936753df029d07922fc919b78b4dbf2b6516a39a</sha1>
  </file>
  <file name="02 - Asteroid A' Comin'  [Rise]_spectrogram.png" source="derivative">
    <format>Spectrogram</format>
    <original>02 - Asteroid A' Comin'  [Rise].mp3</original>
    <mtime>1593568508</mtime>
    <size>295548</size>
    <md5>a6a70edf3deb17538790b48d0eb7a4cb</md5>
    <crc32>45cb6882</crc32>
    <sha1>47ce4a6b3c46b4b91ac48f1c202654b4f42c4db0</sha1>
  </file>
  <file name="03 - Up on the Roof.afpk" source="derivative">
    <format>Columbia Peaks</format>
    <original>03 - Up on the Roof.mp3</original>
    <mtime>1593568704</mtime>
    <size>23672</size>
    <md5>be5ec73847749caf818bfe3f886cd31a</md5>
    <crc32>ab437179</crc32>
    <sha1>8a35e185a34927f0b2d8c05fa20ac4106dfd1d6a</sha1>
  </file>
  <file name="03 - Up on the Roof.mp3" source="original">
    <mtime>1593565588</mtime>
    <size>5314324</size>
    <md5>ed30beefb45801e67eb1bc24f74a4964</md5>
    <crc32>d95b667f</crc32>
    <sha1>d902f1af8b961abd33dfb2fdb360b468a6246ed0</sha1>
    <format>VBR MP3</format>
    <length>132.52</length>
    <height>200</height>
    <width>200</width>
    <title>Up on the Roof</title>
    <creator>Jay Chattaway</creator>
    <album>Star Trek: Voyager Collection Vol. 1 - Disco 1</album>
    <track>03</track>
    <artist>Jay Chattaway</artist>
    <genre>Soundtrack</genre>
  </file>
  <file name="03 - Up on the Roof.png" source="derivative">
    <format>PNG</format>
    <original>03 - Up on the Roof.mp3</original>
    <mtime>1593568412</mtime>
    <size>27244</size>
    <md5>13f66fee4f30998c5400b32415f90612</md5>
    <crc32>bb0e708d</crc32>
    <sha1>6015d0b34aee28eb492452d696d594047ddd27c2</sha1>
  </file>
  <file name="03 - Up on the Roof_spectrogram.png" source="derivative">
    <format>Spectrogram</format>
    <original>03 - Up on the Roof.mp3</original>
    <mtime>1593568532</mtime>
    <size>294473</size>
    <md5>b77bd0bcab979e584cb92b2f3d89dcb0</md5>
    <crc32>1e5b000d</crc32>
    <sha1>97b4188dbadb9da95415d9610163a77594379b2c</sha1>
  </file>
  <file name="04 - Captain Proton  [Night].afpk" source="derivative">
    <format>Columbia Peaks</format>
    <original>04 - Captain Proton  [Night].mp3</original>
    <mtime>1593568716</mtime>
    <size>26936</size>
    <md5>d005cc7d5568491f2a5a532c60812822</md5>
    <crc32>87bb3580</crc32>
    <sha1>34e246f6eafe32269cc03641d0fa672a200d36ec</sha1>
  </file>
  <file name="04 - Captain Proton  [Night].mp3" source="original">
    <mtime>1593565615</mtime>
    <size>5966358</size>
    <md5>c9650dde6f7bf07d089ac6f940e96801</md5>
    <crc32>997dba3d</crc32>
    <sha1>73f60fa4897f953d10642e8ba62e46a35ddf93b4</sha1>
    <format>VBR MP3</format>
    <length>148.82</length>
    <height>200</height>
    <width>200</width>
    <title>Captain Proton [Night]</title>
    <creator>Jay Chattaway</creator>
    <album>Star Trek: Voyager Collection Vol. 1 - Disco 1</album>
    <track>04</track>
    <artist>Jay Chattaway</artist>
    <genre>Soundtrack</genre>
  </file>
  <file name="04 - Captain Proton  [Night].png" source="derivative">
    <format>PNG</format>
    <original>04 - Captain Proton  [Night].mp3</original>
    <mtime>1593568463</mtime>
    <size>33380</size>
    <md5>986ffdeb6ddd3a5e9be45ee58531eaac</md5>
    <crc32>b14ee26b</crc32>
    <sha1>5b94f07f414bec01b82cbaeddda4235482f4cf74</sha1>
  </file>
  <file name="04 - Captain Proton  [Night]_spectrogram.png" source="derivative">
    <format>Spectrogram</format>
    <original>04 - Captain Proton  [Night].mp3</original>
    <mtime>1593568541</mtime>
    <size>297781</size>
    <md5>641f8e1c5bf9e2e669d6a7afd18c0ec8</md5>
    <crc32>3178be16</crc32>
    <sha1>be7a9e71a71c8435007e1b27895c72bbfdf03d41</sha1>
  </file>
  <file name="05 - Taking Out the Garbage  The Vortex Hop.afpk" source="derivative">
    <format>Columbia Peaks</format>
    <original>05 - Taking Out the Garbage  The Vortex Hop.mp3</original>
    <mtime>1593568733</mtime>
    <size>55600</size>
    <md5>878f83e725b6346b50dba42b0d340ba6</md5>
    <crc32>abbe05fb</crc32>
    <sha1>e28aa45dbd2c0bc4f51f987d5fcf58a015fd3508</sha1>
  </file>
  <file name="05 - Taking Out the Garbage  The Vortex Hop.mp3" source="original">
    <mtime>1593565669</mtime>
    <size>11362243</size>
    <md5>2ff71a0a6a2aec12fab4fbfe7a3fdc0b</md5>
    <crc32>72bf83d5</crc32>
    <sha1>18f377b7b603c9bd65140277af2b02333e6f6ba6</sha1>
    <format>VBR MP3</format>
    <length>283.72</length>
    <height>200</height>
    <width>200</width>
    <title>Taking Out the Garbage / The Vortex Hop</title>
    <creator>Jay Chattaway</creator>
    <album>Star Trek: Voyager Collection Vol. 1 - Disco 1</album>
    <track>05</track>
    <artist>Jay Chattaway</artist>
    <genre>Soundtrack</genre>
  </file>
  <file name="05 - Taking Out the Garbage  The Vortex Hop.png" source="derivative">
    <format>PNG</format>
    <original>05 - Taking Out the Garbage  The Vortex Hop.mp3</original>
    <mtime>1593568431</mtime>
    <size>31345</size>
    <md5>e6c3fc4b4ec42183e982464b0008b339</md5>
    <crc32>b4e1aa31</crc32>
    <sha1>f12794a357ef66405051ab84a9ee7ff8baac58f8</sha1>
  </file>
  <file name="05 - Taking Out the Garbage  The Vortex Hop_spectrogram.png" source="derivative">
    <format>Spectrogram</format>
    <original>05 - Taking Out the Garbage  The Vortex Hop.mp3</original>
    <mtime>1593568564</mtime>
    <size>301765</size>
    <md5>c7294b3a21124bcace2703d742a2f6e7</md5>
    <crc32>44af4e89</crc32>
    <sha1>2d7c361ba8f15267341811942d17beecc597235e</sha1>
  </file>
  <file name="06 - Aliens Attack  [Equinox, Part I &amp; II].afpk" source="derivative">
    <format>Columbia Peaks</format>
    <original>06 - Aliens Attack  [Equinox, Part I &amp; II].mp3</original>
    <mtime>1593568745</mtime>
    <size>11688</size>
    <md5>99def879ec8fad4be3027a7634488241</md5>
    <crc32>2a9dcd85</crc32>
    <sha1>a9e4516944fe5be66593e84bd4075040bb47c6e9</sha1>
  </file>
  <file name="06 - Aliens Attack  [Equinox, Part I &amp; II].mp3" source="original">
    <mtime>1593565685</mtime>
    <size>2925733</size>
    <md5>2ea4b33e03ca8e79ffe30145d09c3e88</md5>
    <crc32>1a2ea3ee</crc32>
    <sha1>9901dc1d9891492eeafa29295888adf6bcb2280b</sha1>
    <format>VBR MP3</format>
    <length>72.8</length>
    <height>200</height>
    <width>200</width>
    <title>Aliens Attack [Equinox, Part I &amp; II]</title>
    <creator>Jay Chattaway</creator>
    <album>Star Trek: Voyager Collection Vol. 1 - Disco 1</album>
    <track>06</track>
    <artist>Jay Chattaway</artist>
    <genre>Soundtrack</genre>
  </file>
  <file name="06 - Aliens Attack  [Equinox, Part I &amp; II].png" source="derivative">
    <format>PNG</format>
    <original>06 - Aliens Attack  [Equinox, Part I &amp; II].mp3</original>
    <mtime>1593568440</mtime>
    <size>30994</size>
    <md5>460a932750395bdff1bd0aef2dc6ebe1</md5>
    <crc32>c879c8f3</crc32>
    <sha1>30f28dceb2824da2810534f7a70297edc45d61ed</sha1>
  </file>
  <file name="06 - Aliens Attack  [Equinox, Part I &amp; II]_spectrogram.png" source="derivative">
    <format>Spectrogram</format>
    <original>06 - Aliens Attack  [Equinox, Part I &amp; II].mp3</original>
    <mtime>1593568575</mtime>
    <size>305327</size>
    <md5>08510cb723c4c3f6647f46005247ad32</md5>
    <crc32>91789775</crc32>
    <sha1>91411b2434499da95c8e1c4185ffed32b9813230</sha1>
  </file>
  <file name="07 - Ransom Explains Crime.afpk" source="derivative">
    <format>Columbia Peaks</format>
    <original>07 - Ransom Explains Crime.mp3</original>
    <mtime>1593568751</mtime>
    <size>40696</size>
    <md5>2b5ce94bff04057d701be58c08e85dff</md5>
    <crc32>fac7771c</crc32>
    <sha1>eee0312b9e98f63337f902884b7feee9e54d2044</sha1>
  </file>
  <file name="07 - Ransom Explains Crime.mp3" source="original">
    <mtime>1593565717</mtime>
    <size>6991399</size>
    <md5>8068ac534987eb89e44b67098bbaca2a</md5>
    <crc32>e96dcf32</crc32>
    <sha1>905d81ccf56bf356fe51cb05477bc6aa95ce99ce</sha1>
    <format>VBR MP3</format>
    <length>174.45</length>
    <height>200</height>
    <width>200</width>
    <title>Ransom Explains Crime</title>
    <creator>Jay Chattaway</creator>
    <album>Star Trek: Voyager Collection Vol. 1 - Disco 1</album>
    <track>07</track>
    <artist>Jay Chattaway</artist>
    <genre>Soundtrack</genre>
  </file>
  <file name="07 - Ransom Explains Crime.png" source="derivative">
    <format>PNG</format>
    <original>07 - Ransom Explains Crime.mp3</original>
    <mtime>1593568435</mtime>
    <size>24560</size>
    <md5>b743416a6e57bb96d7e12faee2aa01f6</md5>
    <crc32>90b55f56</crc32>
    <sha1>3001c5a9335747707e0fc63ef4c2dabb4589b6d3</sha1>
  </file>
  <file name="07 - Ransom Explains Crime_spectrogram.png" source="derivative">
    <format>Spectrogram</format>
    <original>07 - Ransom Explains Crime.mp3</original>
    <mtime>1593568550</mtime>
    <size>272916</size>
    <md5>c75be503e23ce8e9c0f722aa8a2457e5</md5>
    <crc32>be5e6535</crc32>
    <sha1>34eeb478caead4ac5d94a11e4da423096a06347d</sha1>
  </file>
  <file name="08 - Equinox Crew Escapes  Equinox Warps Away.afpk" source="derivative">
    <format>Columbia Peaks</format>
    <original>08 - Equinox Crew Escapes  Equinox Warps Away.mp3</original>
    <mtime>1593568693</mtime>
    <size>66352</size>
    <md5>17adf21447d67f3bdb4688ab4d282a68</md5>
    <crc32>b9a5bfbf</crc32>
    <sha1>a267a337ee17794c7b139daa4d6b0bcffcf286c6</sha1>
  </file>
  <file name="08 - Equinox Crew Escapes  Equinox Warps Away.mp3" source="original">
    <mtime>1593565774</mtime>
    <size>13406068</size>
    <md5>3649b8076eb298391fd2f65f46c3d6d1</md5>
    <crc32>f1f0d128</crc32>
    <sha1>0961b2b156cb2084ad13bdd5accc08520f5c0810</sha1>
    <format>VBR MP3</format>
    <length>334.81</length>
    <height>200</height>
    <width>200</width>
    <title>Equinox Crew Escapes / Equinox Warps Away</title>
    <creator>Jay Chattaway</creator>
    <album>Star Trek: Voyager Collection Vol. 1 - Disco 1</album>
    <track>08</track>
    <artist>Jay Chattaway</artist>
    <genre>Soundtrack</genre>
  </file>
  <file name="08 - Equinox Crew Escapes  Equinox Warps Away.png" source="derivative">
    <format>PNG</format>
    <original>08 - Equinox Crew Escapes  Equinox Warps Away.mp3</original>
    <mtime>1593568445</mtime>
    <size>31094</size>
    <md5>4aa63759fa5efb964609581c5a4fb28e</md5>
    <crc32>0b13cb82</crc32>
    <sha1>e8f438a39d851a630d37a8358a0210a8a8b99bd9</sha1>
  </file>
  <file name="08 - Equinox Crew Escapes  Equinox Warps Away_spectrogram.png" source="derivative">
    <format>Spectrogram</format>
    <original>08 - Equinox Crew Escapes  Equinox Warps Away.mp3</original>
    <mtime>1593568512</mtime>
    <size>304524</size>
    <md5>dc4db38c684367a9f996f92d84f0dc34</md5>
    <crc32>8fcf8f53</crc32>
    <sha1>80daff4b32e7114d1230ff62ce3e2daa729b2d71</sha1>
  </file>
  <file name="09 - Recap--Teaser.afpk" source="derivative">
    <format>Columbia Peaks</format>
    <original>09 - Recap--Teaser.mp3</original>
    <mtime>1593568620</mtime>
    <size>30176</size>
    <md5>78c21a51b804a44a7196eccc6d4084a6</md5>
    <crc32>93ddc92c</crc32>
    <sha1>c4358d24662721d9b711de8efa7f464c82643ade</sha1>
  </file>
  <file name="09 - Recap--Teaser.mp3" source="original">
    <mtime>1593565803</mtime>
    <size>6255775</size>
    <md5>9ccd5f03977bb770eec842f853b517c9</md5>
    <crc32>e3ac59aa</crc32>
    <sha1>404d4458fb30d90d7c5fc1edd2066c3af069afa6</sha1>
    <format>VBR MP3</format>
    <length>156.06</length>
    <height>200</height>
    <width>200</width>
    <title>Recap--Teaser</title>
    <creator>Jay Chattaway</creator>
    <album>Star Trek: Voyager Collection Vol. 1 - Disco 1</album>
    <track>09</track>
    <artist>Jay Chattaway</artist>
    <genre>Soundtrack</genre>
  </file>
  <file name="09 - Recap--Teaser.png" source="derivative">
    <format>PNG</format>
    <original>09 - Recap--Teaser.mp3</original>
    <mtime>1593568449</mtime>
    <size>31618</size>
    <md5>c23c53622251e21628c27ac203a6d306</md5>
    <crc32>3c106752</crc32>
    <sha1>c935b9d2fe56d7d30017f477ffe3050b4074e299</sha1>
  </file>
  <file name="09 - Recap--Teaser_spectrogram.png" source="derivative">
    <format>Spectrogram</format>
    <original>09 - Recap--Teaser.mp3</original>
    <mtime>1593568589</mtime>
    <size>301483</size>
    <md5>6bd8fb365fec1c6391c4aaff66f83711</md5>
    <crc32>9b437b69</crc32>
    <sha1>49200052ba3b95074be97dbf416a7f40fc21845b</sha1>
  </file>
  <file name="10 - Feeling Guilty.afpk" source="derivative">
    <format>Columbia Peaks</format>
    <original>10 - Feeling Guilty.mp3</original>
    <mtime>1593568709</mtime>
    <size>22432</size>
    <md5>52d659bae5bb05f098dfbc667787cdda</md5>
    <crc32>b7146dd2</crc32>
    <sha1>a7baa5d8d63a05c431c47e59a866455941f42ea3</sha1>
  </file>
  <file name="10 - Feeling Guilty.mp3" source="original">
    <mtime>1593565823</mtime>
    <size>3760561</size>
    <md5>680dc00bd5347e2f4c23bc1cbd1e4843</md5>
    <crc32>faff8fc0</crc32>
    <sha1>985aa948c9e7e9e75db20c80843ec9f6ab4c07b1</sha1>
    <format>VBR MP3</format>
    <length>93.68</length>
    <height>200</height>
    <width>200</width>
    <title>Feeling Guilty</title>
    <creator>Jay Chattaway</creator>
    <album>Star Trek: Voyager Collection Vol. 1 - Disco 1</album>
    <track>10</track>
    <artist>Jay Chattaway</artist>
    <genre>Soundtrack</genre>
  </file>
  <file name="10 - Feeling Guilty.png" source="derivative">
    <format>PNG</format>
    <original>10 - Feeling Guilty.mp3</original>
    <mtime>1593568454</mtime>
    <size>22198</size>
    <md5>61d91a39575100d79227142c207e7bc3</md5>
    <crc32>60d973dd</crc32>
    <sha1>59cd9d8656474fe90f918994bb0d86b6edf723c6</sha1>
  </file>
  <file name="10 - Feeling Guilty_spectrogram.png" source="derivative">
    <format>Spectrogram</format>
    <original>10 - Feeling Guilty.mp3</original>
    <mtime>1593568535</mtime>
    <size>278543</size>
    <md5>55e7978e4711c503894b285543c2b70b</md5>
    <crc32>536b31cb</crc32>
    <sha1>b975a274be61b57f23772ed20fc631fe1eacea0b</sha1>
  </file>
  <file name="11 - Let the Battle Begin  Ransom Makes Amends.afpk" source="derivative">
    <format>Columbia Peaks</format>
    <original>11 - Let the Battle Begin  Ransom Makes Amends.mp3</original>
    <mtime>1593568772</mtime>
    <size>72344</size>
    <md5>8f323291147a1779eb9db4f56c7ca25a</md5>
    <crc32>0ebc4077</crc32>
    <sha1>14146a31a060c9220f722c204e9406f1fa10b84e</sha1>
  </file>
  <file name="11 - Let the Battle Begin  Ransom Makes Amends.mp3" source="original">
    <mtime>1593565885</mtime>
    <size>14005841</size>
    <md5>af461dc5051aae766412a9ddb8888049</md5>
    <crc32>070b7ba2</crc32>
    <sha1>a10f6178edf0071623e66b9c44135cbb0f193121</sha1>
    <format>VBR MP3</format>
    <length>349.81</length>
    <height>200</height>
    <width>200</width>
    <title>Let the Battle Begin / Ransom Makes Amends</title>
    <creator>Jay Chattaway</creator>
    <album>Star Trek: Voyager Collection Vol. 1 - Disco 1</album>
    <track>11</track>
    <artist>Jay Chattaway</artist>
    <genre>Soundtrack</genre>
  </file>
  <file name="11 - Let the Battle Begin  Ransom Makes Amends.png" source="derivative">
    <format>PNG</format>
    <original>11 - Let the Battle Begin  Ransom Makes Amends.mp3</original>
    <mtime>1593568393</mtime>
    <size>32519</size>
    <md5>b79d140e62934d703e2ba62b015bb1fc</md5>
    <crc32>b27463c3</crc32>
    <sha1>58f0ef27fb7b672088be5b33345a3475e6e4e383</sha1>
  </file>
  <file name="11 - Let the Battle Begin  Ransom Makes Amends_spectrogram.png" source="derivative">
    <format>Spectrogram</format>
    <original>11 - Let the Battle Begin  Ransom Makes Amends.mp3</original>
    <mtime>1593568555</mtime>
    <size>299630</size>
    <md5>8d98cf61f5c5b6442dd3e548ea0139ca</md5>
    <crc32>146cdd9f</crc32>
    <sha1>f09dde38ff5b2589e8f91c241c96e075063f16b0</sha1>
  </file>
  <file name="12 - Hologrid Tag  [Pathfinder].afpk" source="derivative">
    <format>Columbia Peaks</format>
    <original>12 - Hologrid Tag  [Pathfinder].mp3</original>
    <mtime>1593568654</mtime>
    <size>45112</size>
    <md5>f7140bb36906e99fd0d3ce38d4c91a47</md5>
    <crc32>0e3da6b7</crc32>
    <sha1>89963ff6dc727b672144a7fa6aec306c9695e144</sha1>
  </file>
  <file name="12 - Hologrid Tag  [Pathfinder].mp3" source="original">
    <mtime>1593565928</mtime>
    <size>9481401</size>
    <md5>89068d730933f8ef5b53d5a3542f7ec1</md5>
    <crc32>51f0729f</crc32>
    <sha1>35b31d7d372100c56933ea529d2e8f44fafb420e</sha1>
    <format>VBR MP3</format>
    <length>236.7</length>
    <height>200</height>
    <width>200</width>
    <title>Hologrid Tag [Pathfinder]</title>
    <creator>Jay Chattaway</creator>
    <album>Star Trek: Voyager Collection Vol. 1 - Disco 1</album>
    <track>12</track>
    <artist>Jay Chattaway</artist>
    <genre>Soundtrack</genre>
  </file>
  <file name="12 - Hologrid Tag  [Pathfinder].png" source="derivative">
    <format>PNG</format>
    <original>12 - Hologrid Tag  [Pathfinder].mp3</original>
    <mtime>1593568383</mtime>
    <size>31627</size>
    <md5>5da3679ff7463f210356b6523d678759</md5>
    <crc32>fc8feccc</crc32>
    <sha1>b36a63745c25c0e74350449a18cd867cf268c560</sha1>
  </file>
  <file name="12 - Hologrid Tag  [Pathfinder]_spectrogram.png" source="derivative">
    <format>Spectrogram</format>
    <original>12 - Hologrid Tag  [Pathfinder].mp3</original>
    <mtime>1593568586</mtime>
    <size>292013</size>
    <md5>10bce2dd99e92bf25395c47293b438dd</md5>
    <crc32>8ea87781</crc32>
    <sha1>b5f51bf28dfd3e69ca0c31e142abd579cecd8c5f</sha1>
  </file>
  <file name="13 - Voyager Gets Message.afpk" source="derivative">
    <format>Columbia Peaks</format>
    <original>13 - Voyager Gets Message.mp3</original>
    <mtime>1593568614</mtime>
    <size>53120</size>
    <md5>32c04c2bef8a39e2f1743a013f4a189e</md5>
    <crc32>e7b832a8</crc32>
    <sha1>6dc2c1ececc1fb5f436b9a74a45db85c3de8d1e3</sha1>
  </file>
  <file name="13 - Voyager Gets Message.mp3" source="original">
    <mtime>1593565970</mtime>
    <size>9394662</size>
    <md5>e110b2278049dfa0e9f6befb0cc9f394</md5>
    <crc32>8a1b2608</crc32>
    <sha1>fa5a0c727e0989573a7b4f2623f0505fcadebcb3</sha1>
    <format>VBR MP3</format>
    <length>234.53</length>
    <height>200</height>
    <width>200</width>
    <title>Voyager Gets Message</title>
    <creator>Jay Chattaway</creator>
    <album>Star Trek: Voyager Collection Vol. 1 - Disco 1</album>
    <track>13</track>
    <artist>Jay Chattaway</artist>
    <genre>Soundtrack</genre>
  </file>
  <file name="13 - Voyager Gets Message.png" source="derivative">
    <format>PNG</format>
    <original>13 - Voyager Gets Message.mp3</original>
    <mtime>1593568490</mtime>
    <size>29464</size>
    <md5>cbaeebc4bbc8b4140f37861c17573542</md5>
    <crc32>c7bfd033</crc32>
    <sha1>e8965f209f01d50b88870fd5a9e90c09b8599d3b</sha1>
  </file>
  <file name="13 - Voyager Gets Message_spectrogram.png" source="derivative">
    <format>Spectrogram</format>
    <original>13 - Voyager Gets Message.mp3</original>
    <mtime>1593568520</mtime>
    <size>283340</size>
    <md5>c3ad2f015de55b5eeccacaa5e365c921</md5>
    <crc32>b025ad18</crc32>
    <sha1>4c6fd7d7a85b302ec1f81cae8bb6d46621a9dc4b</sha1>
  </file>
  <file name="14 - Seamus Sees All  Rattled Seamus Drinks  Jane Likes Rings  Seamus Follows Paris.afpk" source="derivative">
    <format>Columbia Peaks</format>
    <original>14 - Seamus Sees All  Rattled Seamus Drinks  Jane Likes Rings  Seamus Follows Paris.mp3</original>
    <mtime>1593568762</mtime>
    <size>35000</size>
    <md5>3f48f6e349c16ee037dc2d206c4bc3f3</md5>
    <crc32>45929366</crc32>
    <sha1>e08d096a0d7f56717ccd032a24d476b3b7a5e02e</sha1>
  </file>
  <file name="14 - Seamus Sees All  Rattled Seamus Drinks  Jane Likes Rings  Seamus Follows Paris.mp3" source="original">
    <mtime>1593566007</mtime>
    <size>7752205</size>
    <md5>687a3a1ce5be63497efccc1889e68e78</md5>
    <crc32>c152d259</crc32>
    <sha1>abfb4c917fd82e198046d09ba1568951efd88abe</sha1>
    <format>VBR MP3</format>
    <length>193.46</length>
    <height>200</height>
    <width>200</width>
    <title>Seamus Sees All / Rattled Seamus Drinks / Jane Likes Rings / Seamus Follows Paris</title>
    <creator>Jay Chattaway</creator>
    <album>Star Trek: Voyager Collection Vol. 1 - Disco 1</album>
    <track>14</track>
    <artist>Jay Chattaway</artist>
    <genre>Soundtrack</genre>
  </file>
  <file name="14 - Seamus Sees All  Rattled Seamus Drinks  Jane Likes Rings  Seamus Follows Paris.png" source="derivative">
    <format>PNG</format>
    <original>14 - Seamus Sees All  Rattled Seamus Drinks  Jane Likes Rings  Seamus Follows Paris.mp3</original>
    <mtime>1593568387</mtime>
    <size>31424</size>
    <md5>0db30012e9046463a1092e7e9929f561</md5>
    <crc32>d808f815</crc32>
    <sha1>2cb765371bcec463e48c00815e8994fc797da6a3</sha1>
  </file>
  <file name="14 - Seamus Sees All  Rattled Seamus Drinks  Jane Likes Rings  Seamus Follows Paris_spectrogram.png" source="derivative">
    <format>Spectrogram</format>
    <original>14 - Seamus Sees All  Rattled Seamus Drinks  Jane Likes Rings  Seamus Follows Paris.mp3</original>
    <mtime>1593568516</mtime>
    <size>300881</size>
    <md5>5e1afded1f23acbdcb3c64e74da72ffb</md5>
    <crc32>526f15c8</crc32>
    <sha1>5bebee1ea6eb6fdcdd1327ca5da48543dd9c999b</sha1>
  </file>
  <file name="15 - Maggie Returns to CartBefuddled  MaggieKatie Comes to TeaDemands for Truth.afpk" source="derivative">
    <format>Columbia Peaks</format>
    <original>15 - Maggie Returns to CartBefuddled  MaggieKatie Comes to TeaDemands for Truth.mp3</original>
    <mtime>1593568756</mtime>
    <size>13904</size>
    <md5>735e0ee47fa24343c1fcf0a1a4e338fa</md5>
    <crc32>65762642</crc32>
    <sha1>b91d1ee1de1649df5c20c27241ac68e80ba39560</sha1>
  </file>
  <file name="15 - Maggie Returns to CartBefuddled  MaggieKatie Comes to TeaDemands for Truth.mp3" source="original">
    <mtime>1593566023</mtime>
    <size>2774395</size>
    <md5>a8ab064c12562fa7bf4b7adfcaf64689</md5>
    <crc32>2019135b</crc32>
    <sha1>7e9d71f863a285db5fcbd1ad04ffd6ef35ab4535</sha1>
    <format>VBR MP3</format>
    <length>69.02</length>
    <height>200</height>
    <width>200</width>
    <title>Maggie Returns to Cart/Befuddled Maggie/Katie Comes to Tea/Demands for Truth</title>
    <creator>Jay Chattaway</creator>
    <album>Star Trek: Voyager Collection Vol. 1 - Disco 1</album>
    <track>15</track>
    <artist>Jay Chattaway</artist>
    <genre>Soundtrack</genre>
  </file>
  <file name="15 - Maggie Returns to CartBefuddled  MaggieKatie Comes to TeaDemands for Truth.png" source="derivative">
    <format>PNG</format>
    <original>15 - Maggie Returns to CartBefuddled  MaggieKatie Comes to TeaDemands for Truth.mp3</original>
    <mtime>1593568481</mtime>
    <size>21084</size>
    <md5>bfb28a6e8e83f27874e390e7a91c1fd2</md5>
    <crc32>efe24643</crc32>
    <sha1>c331774459ff75b45846c12c4e44e83d06237a79</sha1>
  </file>
  <file name="15 - Maggie Returns to CartBefuddled  MaggieKatie Comes to TeaDemands for Truth_spectrogram.png" source="derivative">
    <format>Spectrogram</format>
    <original>15 - Maggie Returns to CartBefuddled  MaggieKatie Comes to TeaDemands for Truth.mp3</original>
    <mtime>1593568566</mtime>
    <size>281632</size>
    <md5>c862e7c42afca3d21d2ec6d6f2953c35</md5>
    <crc32>d81ef691</crc32>
    <sha1>9f4aaf63af75c6612a998637221dfa0acd125972</sha1>
  </file>
  <file name="16 - Tending to His Flock  Doc Spills the Beans.afpk" source="derivative">
    <format>Columbia Peaks</format>
    <original>16 - Tending to His Flock  Doc Spills the Beans.mp3</original>
    <mtime>1593568740</mtime>
    <size>36328</size>
    <md5>4ec061841dd777250f8e15fc548be64b</md5>
    <crc32>83ad7da1</crc32>
    <sha1>17ca768a62751779d1c80ec2fec689796fc6fa79</sha1>
  </file>
  <file name="16 - Tending to His Flock  Doc Spills the Beans.mp3" source="original">
    <mtime>1593566060</mtime>
    <size>7840945</size>
    <md5>6bdcfeb12c72840488ab9ca901ac65d6</md5>
    <crc32>67651482</crc32>
    <sha1>b4826a93c49fbf8954800c97fd0edc2d75973c56</sha1>
    <format>VBR MP3</format>
    <length>195.68</length>
    <height>200</height>
    <width>200</width>
    <title>Tending to His Flock / Doc Spills the Beans</title>
    <creator>Jay Chattaway</creator>
    <album>Star Trek: Voyager Collection Vol. 1 - Disco 1</album>
    <track>16</track>
    <artist>Jay Chattaway</artist>
    <genre>Soundtrack</genre>
  </file>
  <file name="16 - Tending to His Flock  Doc Spills the Beans.png" source="derivative">
    <format>PNG</format>
    <original>16 - Tending to His Flock  Doc Spills the Beans.mp3</original>
    <mtime>1593568467</mtime>
    <size>28066</size>
    <md5>0802dfa36e7009cb388fc628603fdaa6</md5>
    <crc32>d7c9ce5a</crc32>
    <sha1>d38958d7f90a5ee4267aa3bb997e74ff770ddbf4</sha1>
  </file>
  <file name="16 - Tending to His Flock  Doc Spills the Beans_spectrogram.png" source="derivative">
    <format>Spectrogram</format>
    <original>16 - Tending to His Flock  Doc Spills the Beans.mp3</original>
    <mtime>1593568530</mtime>
    <size>297076</size>
    <md5>c645172f7a61f6e689ca658c1ac3e947</md5>
    <crc32>551d5480</crc32>
    <sha1>804a771861dc36c2b209e772cc995d99bea8928d</sha1>
  </file>
  <file name="17 - Michael Tricks Them  Time to Be Creative  Angry Mob.afpk" source="derivative">
    <format>Columbia Peaks</format>
    <original>17 - Michael Tricks Them  Time to Be Creative  Angry Mob.mp3</original>
    <mtime>1593568626</mtime>
    <size>25152</size>
    <md5>0528c397589faa070416dc213f610518</md5>
    <crc32>6c0d5abb</crc32>
    <sha1>264fa2815876bb45c45126d9446770dea11f2177</sha1>
  </file>
  <file name="17 - Michael Tricks Them  Time to Be Creative  Angry Mob.mp3" source="original">
    <mtime>1593566085</mtime>
    <size>4948688</size>
    <md5>15a08204db26b2c6e0f6dacc8be9bebb</md5>
    <crc32>41055822</crc32>
    <sha1>cf02d0396b205cd891e496e14fc61d7d2379ae21</sha1>
    <format>VBR MP3</format>
    <length>123.38</length>
    <height>200</height>
    <width>200</width>
    <title>Michael Tricks Them / Time to Be Creative / Angry Mob</title>
    <creator>Jay Chattaway</creator>
    <album>Star Trek: Voyager Collection Vol. 1 - Disco 1</album>
    <track>17</track>
    <artist>Jay Chattaway</artist>
    <genre>Soundtrack</genre>
  </file>
  <file name="17 - Michael Tricks Them  Time to Be Creative  Angry Mob.png" source="derivative">
    <format>PNG</format>
    <original>17 - Michael Tricks Them  Time to Be Creative  Angry Mob.mp3</original>
    <mtime>1593568478</mtime>
    <size>25697</size>
    <md5>89cc7dfb37c5aaf7e4334773b13d52b1</md5>
    <crc32>b05a44d5</crc32>
    <sha1>96cf8cbea28bbd929e597d417762386fba76d05c</sha1>
  </file>
  <file name="17 - Michael Tricks Them  Time to Be Creative  Angry Mob_spectrogram.png" source="derivative">
    <format>Spectrogram</format>
    <original>17 - Michael Tricks Them  Time to Be Creative  Angry Mob.mp3</original>
    <mtime>1593568557</mtime>
    <size>285479</size>
    <md5>c835932a0315ed670d462c9f70d47267</md5>
    <crc32>047a9526</crc32>
    <sha1>92d9721ba4be0df42f779d9f6eb6cd0888c7d40b</sha1>
  </file>
  <file name="18 - Welcome to Voyager  Can't We All Get Along  Michael's Speach  Drinks on the Captain.afpk" source="derivative">
    <format>Columbia Peaks</format>
    <original>18 - Welcome to Voyager  Can't We All Get Along  Michael's Speach  Drinks on the Captain.mp3</original>
    <mtime>1593568683</mtime>
    <size>51016</size>
    <md5>5ed920fb62bd263cbd43cf54b0a34dc9</md5>
    <crc32>147e4d37</crc32>
    <sha1>b5ad181877960467fe06fd45a4967d335e872e04</sha1>
  </file>
  <file name="18 - Welcome to Voyager  Can't We All Get Along  Michael's Speach  Drinks on the Captain.mp3" source="original">
    <mtime>1593566133</mtime>
    <size>9987252</size>
    <md5>df6611ec4e08a9051613e9623b99c099</md5>
    <crc32>52658104</crc32>
    <sha1>505c066f535ef11d0599d8b9ce2c4b51bf7a4c3c</sha1>
    <format>VBR MP3</format>
    <length>249.34</length>
    <height>200</height>
    <width>200</width>
    <title>Welcome to Voyager / Can't We All Get Along / Michael's Speach / Drinks on the Captain</title>
    <creator>Jay Chattaway</creator>
    <album>Star Trek: Voyager Collection Vol. 1 - Disco 1</album>
    <track>18</track>
    <artist>Jay Chattaway</artist>
    <genre>Soundtrack</genre>
  </file>
  <file name="18 - Welcome to Voyager  Can't We All Get Along  Michael's Speach  Drinks on the Captain.png" source="derivative">
    <format>PNG</format>
    <original>18 - Welcome to Voyager  Can't We All Get Along  Michael's Speach  Drinks on the Captain.mp3</original>
    <mtime>1593568486</mtime>
    <size>27410</size>
    <md5>aea79dda53d18cee18f8a0c04125e699</md5>
    <crc32>fe373b42</crc32>
    <sha1>baa407ec50a3267e87f8dea14d3eff9ea17860ae</sha1>
  </file>
  <file name="18 - Welcome to Voyager  Can't We All Get Along  Michael's Speach  Drinks on the Captain_spectrogram.png" source="derivative">
    <format>Spectrogram</format>
    <original>18 - Welcome to Voyager  Can't We All Get Along  Michael's Speach  Drinks on the Captain.mp3</original>
    <mtime>1593568572</mtime>
    <size>284827</size>
    <md5>716183871ac58217e185b876ddf22f74</md5>
    <crc32>61a310df</crc32>
    <sha1>83de88e8a35bba0328b9e34cbf52548d656806ba</sha1>
  </file>
  <file name="19 - Ship Goes Dark  [The Haunting Of Deck Twelve].afpk" source="derivative">
    <format>Columbia Peaks</format>
    <original>19 - Ship Goes Dark  [The Haunting Of Deck Twelve].mp3</original>
    <mtime>1593568675</mtime>
    <size>26616</size>
    <md5>86f3e64880a1867f6164ac4bcd9f4c4d</md5>
    <crc32>4a036f2a</crc32>
    <sha1>f2ebfd2005e916b667d57b2d91a82b74820248a6</sha1>
  </file>
  <file name="19 - Ship Goes Dark  [The Haunting Of Deck Twelve].mp3" source="original">
    <mtime>1593566158</mtime>
    <size>5306027</size>
    <md5>e34f7570dd85d4e4d25635f8d974d056</md5>
    <crc32>453c1e90</crc32>
    <sha1>14a314be0b49a13b38309fb3ca1f3890e5fb8a39</sha1>
    <format>VBR MP3</format>
    <length>132.31</length>
    <height>200</height>
    <width>200</width>
    <title>Ship Goes Dark [The Haunting Of Deck Twelve]</title>
    <creator>Jay Chattaway</creator>
    <album>Star Trek: Voyager Collection Vol. 1 - Disco 1</album>
    <track>19</track>
    <artist>Jay Chattaway</artist>
    <genre>Soundtrack</genre>
  </file>
  <file name="19 - Ship Goes Dark  [The Haunting Of Deck Twelve].png" source="derivative">
    <format>PNG</format>
    <original>19 - Ship Goes Dark  [The Haunting Of Deck Twelve].mp3</original>
    <mtime>1593568495</mtime>
    <size>27755</size>
    <md5>207318a3e67df7ffbf743cf4c8a41e02</md5>
    <crc32>daf695ea</crc32>
    <sha1>efc4a0c8d7500e425af378183e602f934892ea86</sha1>
  </file>
  <file name="19 - Ship Goes Dark  [The Haunting Of Deck Twelve]_spectrogram.png" source="derivative">
    <format>Spectrogram</format>
    <original>19 - Ship Goes Dark  [The Haunting Of Deck Twelve].mp3</original>
    <mtime>1593568592</mtime>
    <size>291389</size>
    <md5>90ad329fc76fabf7f06e18789eb41027</md5>
    <crc32>ab0bc81d</crc32>
    <sha1>1c2ab64d0dbc315f8cf4fa6c55a0c1efd8bc52ff</sha1>
  </file>
  <file name="20 - Abandon Ship  Risking It All  Lifeform's New Home.afpk" source="derivative">
    <format>Columbia Peaks</format>
    <original>20 - Abandon Ship  Risking It All  Lifeform's New Home.mp3</original>
    <mtime>1593568725</mtime>
    <size>74008</size>
    <md5>ab9580731e9f5728f8adc01e20e9d282</md5>
    <crc32>e6615a98</crc32>
    <sha1>c290994a9cd138af4deaef57335950fb51c8aab4</sha1>
  </file>
  <file name="20 - Abandon Ship  Risking It All  Lifeform's New Home.mp3" source="original">
    <mtime>1593566226</mtime>
    <size>14608765</size>
    <md5>93e67ae1f60a0fe994f8e1ed4ffddc35</md5>
    <crc32>5059bcdd</crc32>
    <sha1>f736349111114dc287c10110d7d86f252fad7198</sha1>
    <format>VBR MP3</format>
    <length>364.88</length>
    <height>200</height>
    <width>200</width>
    <title>Abandon Ship / Risking It All / Lifeform's New Home</title>
    <creator>Jay Chattaway</creator>
    <album>Star Trek: Voyager Collection Vol. 1 - Disco 1</album>
    <track>20</track>
    <artist>Jay Chattaway</artist>
    <genre>Soundtrack</genre>
  </file>
  <file name="20 - Abandon Ship  Risking It All  Lifeform's New Home.png" source="derivative">
    <format>PNG</format>
    <original>20 - Abandon Ship  Risking It All  Lifeform's New Home.mp3</original>
    <mtime>1593568473</mtime>
    <size>33706</size>
    <md5>bd6709625f14c6dc659ed75eb6d14665</md5>
    <crc32>6e953624</crc32>
    <sha1>ce55d392d7225331e9340abcdc5d2ac811a038cd</sha1>
  </file>
  <file name="20 - Abandon Ship  Risking It All  Lifeform's New Home_spectrogram.png" source="derivative">
    <format>Spectrogram</format>
    <original>20 - Abandon Ship  Risking It All  Lifeform's New Home.mp3</original>
    <mtime>1593568582</mtime>
    <size>297329</size>
    <md5>5d871ad5da797f9c1215141343fecfc7</md5>
    <crc32>cf2e4313</crc32>
    <sha1>40013f4b2144a7100299134ecf0e0754cce05fe2</sha1>
  </file>
  <file name="21 - Return of Chaotica  Arachnia Saves The Day (Captain Proton)  [Shattered].afpk" source="derivative">
    <format>Columbia Peaks</format>
    <original>21 - Return of Chaotica  Arachnia Saves The Day (Captain Proton)  [Shattered].mp3</original>
    <mtime>1593568641</mtime>
    <size>24656</size>
    <md5>cc62258081fddf07915c271bbbda464f</md5>
    <crc32>64fa4fc6</crc32>
    <sha1>7f0f49d06ece34a3e98c5c13fcb49aec1ca6561c</sha1>
  </file>
  <file name="21 - Return of Chaotica  Arachnia Saves The Day (Captain Proton)  [Shattered].mp3" source="original">
    <mtime>1593566249</mtime>
    <size>4849462</size>
    <md5>e43d4a71591bb26eccf756fff5715c25</md5>
    <crc32>f57608dd</crc32>
    <sha1>6b68a6f98ef4cea40ca00ceefac2793877c3bb48</sha1>
    <format>VBR MP3</format>
    <length>120.89</length>
    <height>200</height>
    <width>200</width>
    <title>Return of Chaotica / Arachnia Saves The Day (Captain Proton) [Shattered]</title>
    <creator>Jay Chattaway</creator>
    <album>Star Trek: Voyager Collection Vol. 1 - Disco 1</album>
    <track>21</track>
    <artist>Jay Chattaway</artist>
    <genre>Soundtrack</genre>
  </file>
  <file name="21 - Return of Chaotica  Arachnia Saves The Day (Captain Proton)  [Shattered].png" source="derivative">
    <format>PNG</format>
    <original>21 - Return of Chaotica  Arachnia Saves The Day (Captain Proton)  [Shattered].mp3</original>
    <mtime>1593568499</mtime>
    <size>28432</size>
    <md5>0a4830e31a25201df6ec9a0b30e45911</md5>
    <crc32>f7a93bf4</crc32>
    <sha1>1b72f039bd41ef1d51ba62c398d3dbf8e8cdc0d0</sha1>
  </file>
  <file name="21 - Return of Chaotica  Arachnia Saves The Day (Captain Proton)  [Shattered]_spectrogram.png" source="derivative">
    <format>Spectrogram</format>
    <original>21 - Return of Chaotica  Arachnia Saves The Day (Captain Proton)  [Shattered].mp3</original>
    <mtime>1593568568</mtime>
    <size>291838</size>
    <md5>927cbd46c0a3cd0175aa7befc682ee23</md5>
    <crc32>4331d1c6</crc32>
    <sha1>8c669a673cb1e7afc39aa7e4a94bd110ce221231</sha1>
  </file>
  <file name="22 - Tuvok's Demise.afpk" source="derivative">
    <format>Columbia Peaks</format>
    <original>22 - Tuvok's Demise.mp3</original>
    <mtime>1593568606</mtime>
    <size>20240</size>
    <md5>23e639fd9531e207a5b1b6fbb775c58f</md5>
    <crc32>93f8f821</crc32>
    <sha1>0e5239e091b02e0c8a1cd194a37455ddfc38d583</sha1>
  </file>
  <file name="22 - Tuvok's Demise.mp3" source="original">
    <mtime>1593566266</mtime>
    <size>3374993</size>
    <md5>597e84cf2bffab5f96dd7e264a46de12</md5>
    <crc32>18567f0e</crc32>
    <sha1>c4e36cbf823ac710392d6a238a98ef3a6a062bfe</sha1>
    <format>VBR MP3</format>
    <length>84.04</length>
    <height>200</height>
    <width>200</width>
    <title>Tuvok's Demise</title>
    <creator>Jay Chattaway</creator>
    <album>Star Trek: Voyager Collection Vol. 1 - Disco 1</album>
    <track>22</track>
    <artist>Jay Chattaway</artist>
    <genre>Soundtrack</genre>
  </file>
  <file name="22 - Tuvok's Demise.png" source="derivative">
    <format>PNG</format>
    <original>22 - Tuvok's Demise.mp3</original>
    <mtime>1593568400</mtime>
    <size>27379</size>
    <md5>eec25d61ba9a685c0115d4233be463d2</md5>
    <crc32>986d8040</crc32>
    <sha1>04d588e5f6a147a52688d66378ed190aa5a034b5</sha1>
  </file>
  <file name="22 - Tuvok's Demise_spectrogram.png" source="derivative">
    <format>Spectrogram</format>
    <original>22 - Tuvok's Demise.mp3</original>
    <mtime>1593568560</mtime>
    <size>271405</size>
    <md5>27f8d1955034dc3ca484c2340db6ce40</md5>
    <crc32>52e089ff</crc32>
    <sha1>c66057cae63f1490fdb7c563c3603a5e1214f1b0</sha1>
  </file>
  <file name="23 - Multiple Attackers  [The Void].afpk" source="derivative">
    <format>Columbia Peaks</format>
    <original>23 - Multiple Attackers  [The Void].mp3</original>
    <mtime>1593568778</mtime>
    <size>36808</size>
    <md5>1b00bdb54af1e70253eb7170d4feb74b</md5>
    <crc32>b6238806</crc32>
    <sha1>30957d8622cda987fd34f39543e2ee9cc770e99b</sha1>
  </file>
  <file name="23 - Multiple Attackers  [The Void].mp3" source="original">
    <mtime>1593566296</mtime>
    <size>6738552</size>
    <md5>71257fd25be61a3860a4c768dc1f4926</md5>
    <crc32>a7db5720</crc32>
    <sha1>7de601cc44ac8436834c30095764aa8a54277c87</sha1>
    <format>VBR MP3</format>
    <length>168.12</length>
    <height>200</height>
    <width>200</width>
    <title>Multiple Attackers [The Void]</title>
    <creator>Jay Chattaway</creator>
    <album>Star Trek: Voyager Collection Vol. 1 - Disco 1</album>
    <track>23</track>
    <artist>Jay Chattaway</artist>
    <genre>Soundtrack</genre>
  </file>
  <file name="23 - Multiple Attackers  [The Void].png" source="derivative">
    <format>PNG</format>
    <original>23 - Multiple Attackers  [The Void].mp3</original>
    <mtime>1593568459</mtime>
    <size>27681</size>
    <md5>c48ab71f03bd1cdc855aa8247c06ebae</md5>
    <crc32>2dc6d676</crc32>
    <sha1>539815ceec257e6885b516159fab92aab1518eef</sha1>
  </file>
  <file name="23 - Multiple Attackers  [The Void]_spectrogram.png" source="derivative">
    <format>Spectrogram</format>
    <original>23 - Multiple Attackers  [The Void].mp3</original>
    <mtime>1593568547</mtime>
    <size>292233</size>
    <md5>013d6e2f9b8ad4e079191b67af0d29b1</md5>
    <crc32>4276e2e3</crc32>
    <sha1>dba53019f13647da1508d5b6ae9fd3692fee209b</sha1>
  </file>
  <file name="24 - Bad Funnel Cake.afpk" source="derivative">
    <format>Columbia Peaks</format>
    <original>24 - Bad Funnel Cake.mp3</original>
    <mtime>1593568636</mtime>
    <size>15848</size>
    <md5>879e48d78977b31072d878a162b8b7fd</md5>
    <crc32>e3442ff9</crc32>
    <sha1>560b2f33743656540e0854ef62597fbe4370dc25</sha1>
  </file>
  <file name="24 - Bad Funnel Cake.mp3" source="original">
    <mtime>1593566315</mtime>
    <size>3515012</size>
    <md5>9cf376887e4cf3bf6289b94b3c081a62</md5>
    <crc32>cffb58e8</crc32>
    <sha1>cccb6ab89a72641ee8f05482c295b6a8958848e5</sha1>
    <format>VBR MP3</format>
    <length>87.54</length>
    <height>200</height>
    <width>200</width>
    <title>Bad Funnel Cake</title>
    <creator>Jay Chattaway</creator>
    <album>Star Trek: Voyager Collection Vol. 1 - Disco 1</album>
    <track>24</track>
    <artist>Jay Chattaway</artist>
    <genre>Soundtrack</genre>
  </file>
  <file name="24 - Bad Funnel Cake.png" source="derivative">
    <format>PNG</format>
    <original>24 - Bad Funnel Cake.mp3</original>
    <mtime>1593568344</mtime>
    <size>27482</size>
    <md5>ddab65d1f48acf3c6cc16343bc778c17</md5>
    <crc32>975cb2d1</crc32>
    <sha1>6ccdd98c0e2336933ea04986bacefb4248fa06c7</sha1>
  </file>
  <file name="24 - Bad Funnel Cake_spectrogram.png" source="derivative">
    <format>Spectrogram</format>
    <original>24 - Bad Funnel Cake.mp3</original>
    <mtime>1593568538</mtime>
    <size>300206</size>
    <md5>9a1a039fccf145b4f5126fdc1018723d</md5>
    <crc32>767e2b03</crc32>
    <sha1>795c6f76c126abb0d1454010538a23a09b3327f4</sha1>
  </file>
  <file name="25 - We're Not Dead Yet.afpk" source="derivative">
    <format>Columbia Peaks</format>
    <original>25 - We're Not Dead Yet.mp3</original>
    <mtime>1593568646</mtime>
    <size>26168</size>
    <md5>5d8131891540a28ed3dc7aa473d6892d</md5>
    <crc32>5d5b528d</crc32>
    <sha1>fb8bbb9f26679c616c9171ad36bc7c5cbea0e45e</sha1>
  </file>
  <file name="25 - We're Not Dead Yet.mp3" source="original">
    <mtime>1593566339</mtime>
    <size>4875475</size>
    <md5>32f4f7f5e0c8c2f1bb150c693f235138</md5>
    <crc32>4af79281</crc32>
    <sha1>392ac66b7741b012f5b74dd48de7c5f6e6543233</sha1>
    <format>VBR MP3</format>
    <length>121.55</length>
    <height>200</height>
    <width>200</width>
    <title>We're Not Dead Yet</title>
    <creator>Jay Chattaway</creator>
    <album>Star Trek: Voyager Collection Vol. 1 - Disco 1</album>
    <track>25</track>
    <artist>Jay Chattaway</artist>
    <genre>Soundtrack</genre>
  </file>
  <file name="25 - We're Not Dead Yet.png" source="derivative">
    <format>PNG</format>
    <original>25 - We're Not Dead Yet.mp3</original>
    <mtime>1593568355</mtime>
    <size>30445</size>
    <md5>02924e3e6b9c4b3be7f53e109c36bd70</md5>
    <crc32>238eca05</crc32>
    <sha1>e37f5ca253e36ff6425170446956f477086374c6</sha1>
  </file>
  <file name="25 - We're Not Dead Yet_spectrogram.png" source="derivative">
    <format>Spectrogram</format>
    <original>25 - We're Not Dead Yet.mp3</original>
    <mtime>1593568527</mtime>
    <size>280536</size>
    <md5>5e105b374b216159e01e035b61d2d163</md5>
    <crc32>1dc0d8e9</crc32>
    <sha1>8f7091fb1672b21a577d4586988994b9b4fdc834</sha1>
  </file>
  <file name="26 - The Alliance Is Born.afpk" source="derivative">
    <format>Columbia Peaks</format>
    <original>26 - The Alliance Is Born.mp3</original>
    <mtime>1593568660</mtime>
    <size>33824</size>
    <md5>371e851a9a80558bc2c6319e3e79a6db</md5>
    <crc32>83833c60</crc32>
    <sha1>18631c9507657511c10d9c833e3cca3ab1492a38</sha1>
  </file>
  <file name="26 - The Alliance Is Born.mp3" source="original">
    <mtime>1593566387</mtime>
    <size>6790777</size>
    <md5>a6cce7000d56f2ad58ad78cd22fa5f90</md5>
    <crc32>fe7fbd56</crc32>
    <sha1>31c1d389ee09137a9dd4f83ee94f5831fd9f1ade</sha1>
    <format>VBR MP3</format>
    <length>169.43</length>
    <height>200</height>
    <width>200</width>
    <title>The Alliance Is Born</title>
    <creator>Jay Chattaway</creator>
    <album>Star Trek: Voyager Collection Vol. 1 - Disco 1</album>
    <track>26</track>
    <artist>Jay Chattaway</artist>
    <genre>Soundtrack</genre>
  </file>
  <file name="26 - The Alliance Is Born.png" source="derivative">
    <format>PNG</format>
    <original>26 - The Alliance Is Born.mp3</original>
    <mtime>1593568374</mtime>
    <size>31780</size>
    <md5>a3f3a872782333990c1cd03003892a2a</md5>
    <crc32>0cc77181</crc32>
    <sha1>8029abd1ccf49cf9326f67042a3c7db98efd19d6</sha1>
  </file>
  <file name="26 - The Alliance Is Born_spectrogram.png" source="derivative">
    <format>Spectrogram</format>
    <original>26 - The Alliance Is Born.mp3</original>
    <mtime>1593568505</mtime>
    <size>300690</size>
    <md5>978dee9e43ce6aacd90dad500b7eacf2</md5>
    <crc32>3f1b92ff</crc32>
    <sha1>72d43d142ff79406566b89dfcd515d17c6e5057c</sha1>
  </file>
  <file name="27 - Montage--Battle Begins  Escaping the Void.afpk" source="derivative">
    <format>Columbia Peaks</format>
    <original>27 - Montage--Battle Begins  Escaping the Void.mp3</original>
    <mtime>1593568669</mtime>
    <size>61064</size>
    <md5>e23dc6c262641403be6d0f24d8ac5ae5</md5>
    <crc32>4dc5643f</crc32>
    <sha1>a41d61f738d632ea017133f7c597d33c44d47df9</sha1>
  </file>
  <file name="27 - Montage--Battle Begins  Escaping the Void.mp3" source="original">
    <mtime>1593566441</mtime>
    <size>11117743</size>
    <md5>0f3e082bb0e68e7fe332403d449c159b</md5>
    <crc32>e0bb8ae4</crc32>
    <sha1>04d9c8bee5e162ea126271c72572ff26fb0ff681</sha1>
    <format>VBR MP3</format>
    <length>277.6</length>
    <height>200</height>
    <width>200</width>
    <title>Montage--Battle Begins / Escaping the Void</title>
    <creator>Jay Chattaway</creator>
    <album>Star Trek: Voyager Collection Vol. 1 - Disco 1</album>
    <track>27</track>
    <artist>Jay Chattaway</artist>
    <genre>Soundtrack</genre>
  </file>
  <file name="27 - Montage--Battle Begins  Escaping the Void.png" source="derivative">
    <format>PNG</format>
    <original>27 - Montage--Battle Begins  Escaping the Void.mp3</original>
    <mtime>1593568379</mtime>
    <size>30616</size>
    <md5>67dacdd81c317a18cd8aa8e099200cf6</md5>
    <crc32>d00865b5</crc32>
    <sha1>298691273009332f846219ade4eb2d1670760137</sha1>
  </file>
  <file name="27 - Montage--Battle Begins  Escaping the Void_spectrogram.png" source="derivative">
    <format>Spectrogram</format>
    <original>27 - Montage--Battle Begins  Escaping the Void.mp3</original>
    <mtime>1593568524</mtime>
    <size>297247</size>
    <md5>e2142769cabb592c7d58658723179f7b</md5>
    <crc32>9ff020c2</crc32>
    <sha1>6a80d81d4d17f48045030902f8aa9526706a0ae5</sha1>
  </file>
  <file name="__ia_thumb.jpg" source="original">
    <mtime>1682400157</mtime>
    <size>19915</size>
    <md5>2a31f9f6f89cd646352becde0ab170df</md5>
    <crc32>2a443bcc</crc32>
    <sha1>f76e93a05b3cb1f75e1b95904782002c1768d29c</sha1>
    <format>Item Tile</format>
    <rotation>0</rotation>
  </file>
  <file name="cover.jpg" source="original">
    <mtime>1593566450</mtime>
    <size>618298</size>
    <md5>8d9025c8e8d581a20cdc61aa16a2f584</md5>
    <crc32>23aadffc</crc32>
    <sha1>30edd04e4f2babf45f030d64201f3c339f7b957e</sha1>
    <format>JPEG</format>
    <rotation>0</rotation>
  </file>
  <file name="cover_thumb.jpg" source="derivative">
    <format>JPEG Thumb</format>
    <original>cover.jpg</original>
    <mtime>1593568328</mtime>
    <size>8403</size>
    <md5>a815d7ac80e44e1deb7c09aa1b317fc0</md5>
    <crc32>b61ba57e</crc32>
    <sha1>3198b758e15ef8d27cae0b625396c4684450e797</sha1>
  </file>
  <file name="voy-collection-vol1-disc1_files.xml" source="original">
    <format>Metadata</format>
    <md5>72c8407dfcd109f38f3b9759d44dffe3</md5>
    <summation>md5</summation>
  </file>
  <file name="voy-collection-vol1-disc1_meta.sqlite" source="original">
    <mtime>1593568138</mtime>
    <size>68608</size>
    <md5>b1bc5f6282ab9587672035fd45f0f817</md5>
    <crc32>fac54f12</crc32>
    <sha1>fdce360ae947b9108136618b7cb213a331f47d2d</sha1>
    <format>Metadata</format>
  </file>
  <file name="voy-collection-vol1-disc1_meta.xml" source="original">
    <mtime>1682400156</mtime>
    <size>820</size>
    <md5>27587f1d8584b0d89666b52d66a1e408</md5>
    <crc32>c1f0a204</crc32>
    <sha1>9e810532ed74d491333267a3f5c4144ce3501a7f</sha1>
    <format>Metadata</format>
  </file>
</files>
