<?xml version="1.0" encoding="UTF-8"?>
<metadata>
  <identifier>metroid-prime-fusion-original-soundtracks</identifier>
  <mediatype>audio</mediatype>
  <collection>hifidelity_soundtracks</collection>
  <creator>Scitron Digital Contents</creator>
  <date>2003-06-18</date>
  <description>GAME STAFF&lt;br /&gt;&lt;br /&gt;METROID PRIME Music&lt;br /&gt;山本 健誌/Kenji Yamamoto (NINTENDO)&lt;br /&gt;久馬 浩一/Kouichi Kyuma (NINTENDO)&lt;br /&gt;&lt;br /&gt;METROID FUSION Music&lt;br /&gt;濱野 美奈子/Minako Hamano (NINTENDO)&lt;br /&gt;藤原 玲/Akira Fujiwara (NINTENDO)&lt;br /&gt;&lt;br /&gt;&lt;br /&gt;CD STAFF&lt;br /&gt;&lt;br /&gt;Producer&lt;br /&gt;八木 貴弘/Takahiro "T.J!" Yagi (Scitron Digital Content Inc.)&lt;br /&gt;&lt;br /&gt;Metroid Fusion Arrange Version Composed by &lt;br /&gt;細江 慎治/Shinji Hosoe (Super Sweep)&lt;br /&gt;&lt;br /&gt;Mastering Engineer&lt;br /&gt;中山 譲/Yuzuru Nakayama (Scitron Digital Content Inc.)&lt;br /&gt;&lt;br /&gt;Recorded at &lt;br /&gt;SCITRON STUDIO SOUNDSHIP&lt;br /&gt;&lt;br /&gt;Design Producer&lt;br /&gt;小田 能知/Nochi Oda (Scitron Digital Content Inc.)&lt;br /&gt;&lt;br /&gt;Designed by&lt;br /&gt;原 邦雄/Kunio Hara (TOM'S)&lt;br /&gt;&lt;br /&gt;Promoted by&lt;br /&gt;高橋 克典/Katsunori Takahashi (Scitron Digital Content Inc.)&lt;br /&gt;外崎 剛/Tsuyoshi Tonosaki (Scitron Digital Content Inc.)&lt;br /&gt;関 美奈子/Minako Seki (Scitron Digital Content Inc.)&lt;br /&gt;&lt;br /&gt;Release Operated by &lt;br /&gt;二田 祐樹/Uki Nita (Scitron Digital Content Inc.)&lt;br /&gt;&lt;br /&gt;BIG THANKS to &lt;br /&gt;ALL NINTENDO STAFF&lt;br /&gt;&lt;br /&gt;Executive Producer&lt;br /&gt;大野 善寛/Yoshihiro Ohno (Scitron Digital Content Inc.)&lt;br /&gt;&lt;br /&gt;&lt;br /&gt;All Rights, including the copylights of Game, Scenario, &lt;br /&gt;Music and Program,reserved by NINTENDO.&lt;br /&gt;Ⓒ2002,2003 Nintendo</description>
  <language>eng</language>
  <scanner>Internet Archive HTML5 Uploader 1.6.4</scanner>
  <subject>Original Soundtrack</subject>
  <subject>Arrangement</subject>
  <title>Metroid Prime &amp; Fusion Original Soundtracks</title>
  <uploader>ngc-archive@protonmail.ch</uploader>
  <publicdate>2022-01-28 23:52:24</publicdate>
  <addeddate>2022-01-28 23:52:24</addeddate>
  <curation>[curator]validator@archive.org[/curator][date]20220129002700[/date][comment]checked for malware[/comment]</curation>
  <year>2003</year>
  <collection>hifidelity</collection>
</metadata>
