<?xml version="1.0" encoding="UTF-8"?>
<files>
  <file name="20.-rainbow-road_archive.torrent" source="metadata">
    <btih>b87a1544ea13f78927bc69cbe8517fc6d7ad4d05</btih>
    <mtime>1691200122</mtime>
    <size>52367</size>
    <md5>710d1c860cfd8eca0b97f80c40cf0447</md5>
    <crc32>18cb2570</crc32>
    <sha1>ed5bf8d7d15ce86156b905f25a4cb57e22849122</sha1>
    <format>Archive BitTorrent</format>
  </file>
  <file name="20.-rainbow-road_files.xml" source="original">
    <format>Metadata</format>
    <md5>0c330b29f8ccf74c22e2297b2afadf3d</md5>
    <summation>md5</summation>
  </file>
  <file name="20.-rainbow-road_meta.sqlite" source="original">
    <mtime>1636284451</mtime>
    <size>229376</size>
    <md5>c8e6007be58eb4797bb969f2ee4ba8d3</md5>
    <crc32>8975911f</crc32>
    <sha1>bd666a84de08b52732f91304a745cd474e0c6809</sha1>
    <format>Metadata</format>
  </file>
  <file name="20.-rainbow-road_meta.xml" source="original">
    <mtime>1691200119</mtime>
    <size>1366</size>
    <md5>a7a9efd4e83bd88fce62658420e81eaa</md5>
    <crc32>a48b8cfe</crc32>
    <sha1>d6ba33ae5923b459d9be932e8a04e8cf76caaa06</sha1>
    <format>Metadata</format>
  </file>
  <file name="20.-rainbow-road_reviews.xml" source="original">
    <mtime>1691200118</mtime>
    <size>1037</size>
    <md5>7c4bf246a4897fb8e0f52b77b4f37f54</md5>
    <crc32>250d018f</crc32>
    <sha1>4fefc3cb63730734d87548ac05a76a29c7c2eff9</sha1>
    <format>Metadata</format>
  </file>
  <file name="Mario Kart Wii Platinum Soundtrack [MP3]/01. Opening Movie.afpk" source="derivative">
    <format>Columbia Peaks</format>
    <original>Mario Kart Wii Platinum Soundtrack [MP3]/01. Opening Movie.mp3</original>
    <mtime>1636294856</mtime>
    <size>16344</size>
    <md5>52bd72c5cd6d8e26734ade65f6dbc530</md5>
    <crc32>4014c235</crc32>
    <sha1>c69029be0b81773aa5ea97ca1ec3575b3a4c43fc</sha1>
  </file>
  <file name="Mario Kart Wii Platinum Soundtrack [MP3]/01. Opening Movie.mp3" source="original">
    <mtime>1636284253</mtime>
    <size>3145602</size>
    <md5>7c22aa673dd775b689cd7efa6b30cd3e</md5>
    <crc32>c5895084</crc32>
    <sha1>afbf0ee36c1db53d37584ff6d45618834d547831</sha1>
    <format>VBR MP3</format>
    <length>71.24</length>
    <title>Opening Movie</title>
    <creator>Asuka Ohta, Ryo Nagamatsu</creator>
    <album>Mario Kart Wii Platinum Soundtrack</album>
    <track>1/43</track>
    <artist>Asuka Ohta, Ryo Nagamatsu</artist>
    <genre>Game Soundtrack</genre>
    <comment>http://sittingonclouds.net</comment>
  </file>
  <file name="Mario Kart Wii Platinum Soundtrack [MP3]/01. Opening Movie.png" source="derivative">
    <format>PNG</format>
    <original>Mario Kart Wii Platinum Soundtrack [MP3]/01. Opening Movie.mp3</original>
    <mtime>1636286636</mtime>
    <size>40707</size>
    <md5>bdbb3e2f76da8e678b8ad4722a9b98c1</md5>
    <crc32>f886b5f4</crc32>
    <sha1>4a8171ade174405dc9cf6410c1a9ad7f45516bbc</sha1>
  </file>
  <file name="Mario Kart Wii Platinum Soundtrack [MP3]/01. Opening Movie_spectrogram.png" source="derivative">
    <format>Spectrogram</format>
    <original>Mario Kart Wii Platinum Soundtrack [MP3]/01. Opening Movie.mp3</original>
    <mtime>1636292217</mtime>
    <size>326727</size>
    <md5>e26f2b368d8c749cfcd5a7604068ad30</md5>
    <crc32>2bb0b725</crc32>
    <sha1>f464737ef77d92063ead38ee74876ba314a35090</sha1>
  </file>
  <file name="Mario Kart Wii Platinum Soundtrack [MP3]/02. Title Screen.afpk" source="derivative">
    <format>Columbia Peaks</format>
    <original>Mario Kart Wii Platinum Soundtrack [MP3]/02. Title Screen.mp3</original>
    <mtime>1636296492</mtime>
    <size>13496</size>
    <md5>6ff95c3f0a7de8cb3a73a07295dd6861</md5>
    <crc32>ebd7555b</crc32>
    <sha1>0c663073ecea81341ef3b2f2645d13ed998892d1</sha1>
  </file>
  <file name="Mario Kart Wii Platinum Soundtrack [MP3]/02. Title Screen.mp3" source="original">
    <mtime>1636284306</mtime>
    <size>3023347</size>
    <md5>ca5fbc4a97630e091e1216626dbd1460</md5>
    <crc32>304a1d34</crc32>
    <sha1>91112b339c13131cc2ff877aa5f5367505891584</sha1>
    <format>VBR MP3</format>
    <length>68.18</length>
    <title>Title Screen</title>
    <creator>Asuka Ohta, Ryo Nagamatsu</creator>
    <album>Mario Kart Wii Platinum Soundtrack</album>
    <track>2/43</track>
    <artist>Asuka Ohta, Ryo Nagamatsu</artist>
    <genre>Game Soundtrack</genre>
    <comment>http://sittingonclouds.net</comment>
  </file>
  <file name="Mario Kart Wii Platinum Soundtrack [MP3]/02. Title Screen.png" source="derivative">
    <format>PNG</format>
    <original>Mario Kart Wii Platinum Soundtrack [MP3]/02. Title Screen.mp3</original>
    <mtime>1636286213</mtime>
    <size>39026</size>
    <md5>a606bb50de7bce0ab48791a4485b24c2</md5>
    <crc32>c9244098</crc32>
    <sha1>bd6470db2844d2b247cb33d9f4ad781c068b3b56</sha1>
  </file>
  <file name="Mario Kart Wii Platinum Soundtrack [MP3]/02. Title Screen_spectrogram.png" source="derivative">
    <format>Spectrogram</format>
    <original>Mario Kart Wii Platinum Soundtrack [MP3]/02. Title Screen.mp3</original>
    <mtime>1636290057</mtime>
    <size>327496</size>
    <md5>ad9e61bd37dbd1f41aa5a12710641893</md5>
    <crc32>c77f70d3</crc32>
    <sha1>525d5dc73034d2d8d0982705583260d5d4ad089a</sha1>
  </file>
  <file name="Mario Kart Wii Platinum Soundtrack [MP3]/03. Options-License Management.afpk" source="derivative">
    <format>Columbia Peaks</format>
    <original>Mario Kart Wii Platinum Soundtrack [MP3]/03. Options-License Management.mp3</original>
    <mtime>1636293018</mtime>
    <size>6816</size>
    <md5>33a647883f5fedb17c0bbe61f983a9b1</md5>
    <crc32>3bea11b2</crc32>
    <sha1>dc83f021011652278f31017c79a9f3023b2f76b8</sha1>
  </file>
  <file name="Mario Kart Wii Platinum Soundtrack [MP3]/03. Options-License Management.mp3" source="original">
    <mtime>1636284309</mtime>
    <size>1713073</size>
    <md5>6eb0597217ee31cca69f95922d63a3b5</md5>
    <crc32>b3a4e8c9</crc32>
    <sha1>70d3e8f214a61182e0c6de343c05b84cc2de21a7</sha1>
    <format>VBR MP3</format>
    <length>35.42</length>
    <title>Options/License Management</title>
    <creator>Asuka Ohta, Ryo Nagamatsu</creator>
    <album>Mario Kart Wii Platinum Soundtrack</album>
    <track>3/43</track>
    <artist>Asuka Ohta, Ryo Nagamatsu</artist>
    <genre>Game Soundtrack</genre>
    <comment>http://sittingonclouds.net</comment>
  </file>
  <file name="Mario Kart Wii Platinum Soundtrack [MP3]/03. Options-License Management.png" source="derivative">
    <format>PNG</format>
    <original>Mario Kart Wii Platinum Soundtrack [MP3]/03. Options-License Management.mp3</original>
    <mtime>1636285423</mtime>
    <size>30053</size>
    <md5>ba90016fff6bdaf9737a227e0ee87256</md5>
    <crc32>f7622612</crc32>
    <sha1>70cb06ef635600c9ca5a29ca9cc468d2832f5c29</sha1>
  </file>
  <file name="Mario Kart Wii Platinum Soundtrack [MP3]/03. Options-License Management_spectrogram.png" source="derivative">
    <format>Spectrogram</format>
    <original>Mario Kart Wii Platinum Soundtrack [MP3]/03. Options-License Management.mp3</original>
    <mtime>1636289031</mtime>
    <size>319348</size>
    <md5>ed02e4eab7ee224528baeb9371dde6e9</md5>
    <crc32>520da28b</crc32>
    <sha1>dbf09c69a176fdcc8ba03a1863ecad65fc89f25a</sha1>
  </file>
  <file name="Mario Kart Wii Platinum Soundtrack [MP3]/04. Main Menu.afpk" source="derivative">
    <format>Columbia Peaks</format>
    <original>Mario Kart Wii Platinum Soundtrack [MP3]/04. Main Menu.mp3</original>
    <mtime>1636294196</mtime>
    <size>28960</size>
    <md5>2c6e5564ba1bf362828ddea3fb4cc14f</md5>
    <crc32>a64e74c0</crc32>
    <sha1>8823401c37694dc3256af200c20cf7c33f899ea7</sha1>
  </file>
  <file name="Mario Kart Wii Platinum Soundtrack [MP3]/04. Main Menu.mp3" source="original">
    <mtime>1636284345</mtime>
    <size>6219684</size>
    <md5>61c3b4faf22dc7de0bda0e461f654bbd</md5>
    <crc32>aea31fd8</crc32>
    <sha1>65ac1a18f417b28ceadb3e6f3767dadd45dc0361</sha1>
    <format>VBR MP3</format>
    <length>148.09</length>
    <title>Main Menu</title>
    <creator>Asuka Ohta, Ryo Nagamatsu</creator>
    <album>Mario Kart Wii Platinum Soundtrack</album>
    <track>4/43</track>
    <artist>Asuka Ohta, Ryo Nagamatsu</artist>
    <genre>Game Soundtrack</genre>
    <comment>http://sittingonclouds.net</comment>
  </file>
  <file name="Mario Kart Wii Platinum Soundtrack [MP3]/04. Main Menu.png" source="derivative">
    <format>PNG</format>
    <original>Mario Kart Wii Platinum Soundtrack [MP3]/04. Main Menu.mp3</original>
    <mtime>1636287780</mtime>
    <size>44957</size>
    <md5>5259bf2fbd4bb026f9af4a6a98348c9a</md5>
    <crc32>c4930eca</crc32>
    <sha1>d9a118b0384fbc99d46ec87424b71ce6e8e50003</sha1>
  </file>
  <file name="Mario Kart Wii Platinum Soundtrack [MP3]/04. Main Menu_spectrogram.png" source="derivative">
    <format>Spectrogram</format>
    <original>Mario Kart Wii Platinum Soundtrack [MP3]/04. Main Menu.mp3</original>
    <mtime>1636289918</mtime>
    <size>306550</size>
    <md5>87bdda29f2ede26026430f0edf8fb8c0</md5>
    <crc32>ea835f7f</crc32>
    <sha1>aac353941cd4189ee43954756d26e4d2ae3a17e8</sha1>
  </file>
  <file name="Mario Kart Wii Platinum Soundtrack [MP3]/05. Course Overview Fanfare.afpk" source="derivative">
    <format>Columbia Peaks</format>
    <original>Mario Kart Wii Platinum Soundtrack [MP3]/05. Course Overview Fanfare.mp3</original>
    <mtime>1636296244</mtime>
    <size>2528</size>
    <md5>30841c5db24a37745623f0cee4fa1cf1</md5>
    <crc32>1ad60a12</crc32>
    <sha1>fa30357f9c3b0f25ecf7cf148c2169a75f624f39</sha1>
  </file>
  <file name="Mario Kart Wii Platinum Soundtrack [MP3]/05. Course Overview Fanfare.mp3" source="original">
    <mtime>1636284348</mtime>
    <size>911630</size>
    <md5>9e6fe1caeea78c80f3c32ee348e5fdac</md5>
    <crc32>3d7ed434</crc32>
    <sha1>322492c102a4ff131611a36bb0110d544c8f87ba</sha1>
    <format>VBR MP3</format>
    <length>15.39</length>
    <title>Course Overview Fanfare</title>
    <creator>Asuka Ohta, Ryo Nagamatsu</creator>
    <album>Mario Kart Wii Platinum Soundtrack</album>
    <track>5/43</track>
    <artist>Asuka Ohta, Ryo Nagamatsu</artist>
    <genre>Game Soundtrack</genre>
    <comment>http://sittingonclouds.net</comment>
  </file>
  <file name="Mario Kart Wii Platinum Soundtrack [MP3]/05. Course Overview Fanfare.png" source="derivative">
    <format>PNG</format>
    <original>Mario Kart Wii Platinum Soundtrack [MP3]/05. Course Overview Fanfare.mp3</original>
    <mtime>1636285000</mtime>
    <size>26239</size>
    <md5>b72e7f60546d40cd4b4a416ae6ce45e9</md5>
    <crc32>080594ed</crc32>
    <sha1>cce93f07066517f7c87c1b0f334bc61deeb02547</sha1>
  </file>
  <file name="Mario Kart Wii Platinum Soundtrack [MP3]/05. Course Overview Fanfare_spectrogram.png" source="derivative">
    <format>Spectrogram</format>
    <original>Mario Kart Wii Platinum Soundtrack [MP3]/05. Course Overview Fanfare.mp3</original>
    <mtime>1636289316</mtime>
    <size>325933</size>
    <md5>20f70b5120cba57f47b5f94082f724db</md5>
    <crc32>64de05b5</crc32>
    <sha1>7db994a92917839bc5b9f21e88217ac01b800db1</sha1>
  </file>
  <file name="Mario Kart Wii Platinum Soundtrack [MP3]/06. Luigi Circuit-Mario Circuit.afpk" source="derivative">
    <format>Columbia Peaks</format>
    <original>Mario Kart Wii Platinum Soundtrack [MP3]/06. Luigi Circuit-Mario Circuit.mp3</original>
    <mtime>1636296013</mtime>
    <size>32808</size>
    <md5>ea2b9f7202eb8434503766dbed5e4a17</md5>
    <crc32>9b17c141</crc32>
    <sha1>a0fb8f3b08732a1344ed4f7dc12dfc14b0cb6a4e</sha1>
  </file>
  <file name="Mario Kart Wii Platinum Soundtrack [MP3]/06. Luigi Circuit-Mario Circuit.mp3" source="original">
    <mtime>1636284262</mtime>
    <size>5511279</size>
    <md5>2036c87bf698c599185792970b8ae8bc</md5>
    <crc32>39e06d3e</crc32>
    <sha1>7560200443aa4477059063a1e5f630ebc441001b</sha1>
    <format>VBR MP3</format>
    <length>130.38</length>
    <title>Luigi Circuit/Mario Circuit</title>
    <creator>Asuka Ohta, Ryo Nagamatsu</creator>
    <album>Mario Kart Wii Platinum Soundtrack</album>
    <track>6/43</track>
    <artist>Asuka Ohta, Ryo Nagamatsu</artist>
    <genre>Game Soundtrack</genre>
    <comment>http://sittingonclouds.net</comment>
  </file>
  <file name="Mario Kart Wii Platinum Soundtrack [MP3]/06. Luigi Circuit-Mario Circuit.png" source="derivative">
    <format>PNG</format>
    <original>Mario Kart Wii Platinum Soundtrack [MP3]/06. Luigi Circuit-Mario Circuit.mp3</original>
    <mtime>1636286101</mtime>
    <size>46802</size>
    <md5>1889a4a9d8498eb45cbc06aad9957117</md5>
    <crc32>a0cc7448</crc32>
    <sha1>897680d67080067f0b9555a1a981643b705e2f9e</sha1>
  </file>
  <file name="Mario Kart Wii Platinum Soundtrack [MP3]/06. Luigi Circuit-Mario Circuit_spectrogram.png" source="derivative">
    <format>Spectrogram</format>
    <original>Mario Kart Wii Platinum Soundtrack [MP3]/06. Luigi Circuit-Mario Circuit.mp3</original>
    <mtime>1636291862</mtime>
    <size>320459</size>
    <md5>2ebee0c9af3ef919822c0a3166d1f01d</md5>
    <crc32>454fb97e</crc32>
    <sha1>6151415708a64262518a6fe11bd8c5ea9849f7bc</sha1>
  </file>
  <file name="Mario Kart Wii Platinum Soundtrack [MP3]/07. Moo Moo Meadows.afpk" source="derivative">
    <format>Columbia Peaks</format>
    <original>Mario Kart Wii Platinum Soundtrack [MP3]/07. Moo Moo Meadows.mp3</original>
    <mtime>1636296408</mtime>
    <size>29344</size>
    <md5>56b9a8d2293a22a0e11c06fb51c26243</md5>
    <crc32>2967a15c</crc32>
    <sha1>c012e87dd69a231603f6a93268614ad1063d3453</sha1>
  </file>
  <file name="Mario Kart Wii Platinum Soundtrack [MP3]/07. Moo Moo Meadows.mp3" source="original">
    <mtime>1636284392</mtime>
    <size>5567680</size>
    <md5>65361fbfc59ef3b7b52413744a57ef29</md5>
    <crc32>6513347c</crc32>
    <sha1>c71ec85b88fa395ba912e425196a06f9bd42042e</sha1>
    <format>VBR MP3</format>
    <length>131.79</length>
    <title>Moo Moo Meadows</title>
    <creator>Asuka Ohta, Ryo Nagamatsu</creator>
    <album>Mario Kart Wii Platinum Soundtrack</album>
    <track>7/43</track>
    <artist>Asuka Ohta, Ryo Nagamatsu</artist>
    <genre>Game Soundtrack</genre>
    <comment>http://sittingonclouds.net</comment>
  </file>
  <file name="Mario Kart Wii Platinum Soundtrack [MP3]/07. Moo Moo Meadows.png" source="derivative">
    <format>PNG</format>
    <original>Mario Kart Wii Platinum Soundtrack [MP3]/07. Moo Moo Meadows.mp3</original>
    <mtime>1636285911</mtime>
    <size>43647</size>
    <md5>2aa842a2fc5bf7c194308980f5f36789</md5>
    <crc32>673640ed</crc32>
    <sha1>3061a0d894978e338c400a73e37b5e102f8e432c</sha1>
  </file>
  <file name="Mario Kart Wii Platinum Soundtrack [MP3]/07. Moo Moo Meadows_spectrogram.png" source="derivative">
    <format>Spectrogram</format>
    <original>Mario Kart Wii Platinum Soundtrack [MP3]/07. Moo Moo Meadows.mp3</original>
    <mtime>1636291122</mtime>
    <size>319337</size>
    <md5>2b420cd66081b201eaa84078fd3772e4</md5>
    <crc32>660e487a</crc32>
    <sha1>8f8923f1a0bd7ab50b893356028400b4c9e3cc35</sha1>
  </file>
  <file name="Mario Kart Wii Platinum Soundtrack [MP3]/08. Mushroom Gorge.afpk" source="derivative">
    <format>Columbia Peaks</format>
    <original>Mario Kart Wii Platinum Soundtrack [MP3]/08. Mushroom Gorge.mp3</original>
    <mtime>1636294012</mtime>
    <size>27936</size>
    <md5>dea360a1e79be23ea88b9a007732220e</md5>
    <crc32>e10a579f</crc32>
    <sha1>eb2b6871b78948c01c2211cff55a13ff83c3716b</sha1>
  </file>
  <file name="Mario Kart Wii Platinum Soundtrack [MP3]/08. Mushroom Gorge.mp3" source="original">
    <mtime>1636284248</mtime>
    <size>4992984</size>
    <md5>4c6cba01d0af2b7c02ede8aad66f8a11</md5>
    <crc32>18009f0a</crc32>
    <sha1>92f153f9773615a257351ab87266b349e065d452</sha1>
    <format>VBR MP3</format>
    <length>117.42</length>
    <title>Mushroom Gorge</title>
    <creator>Asuka Ohta, Ryo Nagamatsu</creator>
    <album>Mario Kart Wii Platinum Soundtrack</album>
    <track>8/43</track>
    <artist>Asuka Ohta, Ryo Nagamatsu</artist>
    <genre>Game Soundtrack</genre>
    <comment>http://sittingonclouds.net</comment>
  </file>
  <file name="Mario Kart Wii Platinum Soundtrack [MP3]/08. Mushroom Gorge.png" source="derivative">
    <format>PNG</format>
    <original>Mario Kart Wii Platinum Soundtrack [MP3]/08. Mushroom Gorge.mp3</original>
    <mtime>1636285793</mtime>
    <size>41990</size>
    <md5>8153686423c742018836a00265c4d735</md5>
    <crc32>a791dfc2</crc32>
    <sha1>21356c44ce440e2c3a508b8b431221a074796861</sha1>
  </file>
  <file name="Mario Kart Wii Platinum Soundtrack [MP3]/08. Mushroom Gorge_spectrogram.png" source="derivative">
    <format>Spectrogram</format>
    <original>Mario Kart Wii Platinum Soundtrack [MP3]/08. Mushroom Gorge.mp3</original>
    <mtime>1636291326</mtime>
    <size>318149</size>
    <md5>211527b7d48075df912f4c196ff325ab</md5>
    <crc32>07789808</crc32>
    <sha1>63ea57bc9b4568e90c4c6f061c32f2789d45e112</sha1>
  </file>
  <file name="Mario Kart Wii Platinum Soundtrack [MP3]/09. Toad's Factory.afpk" source="derivative">
    <format>Columbia Peaks</format>
    <original>Mario Kart Wii Platinum Soundtrack [MP3]/09. Toad's Factory.mp3</original>
    <mtime>1636293370</mtime>
    <size>35424</size>
    <md5>1f16d9432c1f15b62ced71548ce23791</md5>
    <crc32>66957653</crc32>
    <sha1>51500317cc8a10a088d6659c7d08aaf2d9885afe</sha1>
  </file>
  <file name="Mario Kart Wii Platinum Soundtrack [MP3]/09. Toad's Factory.mp3" source="original">
    <mtime>1636284302</mtime>
    <size>6450617</size>
    <md5>0c5ed4ba970a6cf747d184092afdb9f8</md5>
    <crc32>803b0421</crc32>
    <sha1>e511efe1cf9cfa54f42cb10f2a0b0f6f3cd1afee</sha1>
    <format>VBR MP3</format>
    <length>153.86</length>
    <title>Toad's Factory</title>
    <creator>Asuka Ohta, Ryo Nagamatsu</creator>
    <album>Mario Kart Wii Platinum Soundtrack</album>
    <track>9/43</track>
    <artist>Asuka Ohta, Ryo Nagamatsu</artist>
    <genre>Game Soundtrack</genre>
    <comment>http://sittingonclouds.net</comment>
  </file>
  <file name="Mario Kart Wii Platinum Soundtrack [MP3]/09. Toad's Factory.png" source="derivative">
    <format>PNG</format>
    <original>Mario Kart Wii Platinum Soundtrack [MP3]/09. Toad's Factory.mp3</original>
    <mtime>1636285583</mtime>
    <size>47032</size>
    <md5>a8d515e81207dec311669879fc218489</md5>
    <crc32>01c974b7</crc32>
    <sha1>84ab9818346525c53d6c74f5adc233a30236e11e</sha1>
  </file>
  <file name="Mario Kart Wii Platinum Soundtrack [MP3]/09. Toad's Factory_spectrogram.png" source="derivative">
    <format>Spectrogram</format>
    <original>Mario Kart Wii Platinum Soundtrack [MP3]/09. Toad's Factory.mp3</original>
    <mtime>1636291550</mtime>
    <size>324436</size>
    <md5>02e4a83b342233f58ad6d3d7970c5376</md5>
    <crc32>d227c57a</crc32>
    <sha1>6683969b4ba50cabdd69a8a404ac5d067a58186b</sha1>
  </file>
  <file name="Mario Kart Wii Platinum Soundtrack [MP3]/10. Coconut Mall.afpk" source="derivative">
    <format>Columbia Peaks</format>
    <original>Mario Kart Wii Platinum Soundtrack [MP3]/10. Coconut Mall.mp3</original>
    <mtime>1636293645</mtime>
    <size>35496</size>
    <md5>c3371169a7e399ac9217d57ca96b60ac</md5>
    <crc32>c5bad2b1</crc32>
    <sha1>0f7b988ce60145335a1cd62f22975f7faa6c418c</sha1>
  </file>
  <file name="Mario Kart Wii Platinum Soundtrack [MP3]/10. Coconut Mall.mp3" source="original">
    <mtime>1636284218</mtime>
    <size>5789193</size>
    <md5>5f31302d4bf798121305f665caa7735e</md5>
    <crc32>c2997fa0</crc32>
    <sha1>fd713569d1204febb0f27812c38bc3cc920a6627</sha1>
    <format>VBR MP3</format>
    <length>137.33</length>
    <title>Coconut Mall</title>
    <creator>Asuka Ohta, Ryo Nagamatsu</creator>
    <album>Mario Kart Wii Platinum Soundtrack</album>
    <track>10/43</track>
    <artist>Asuka Ohta, Ryo Nagamatsu</artist>
    <genre>Game Soundtrack</genre>
    <comment>http://sittingonclouds.net</comment>
  </file>
  <file name="Mario Kart Wii Platinum Soundtrack [MP3]/10. Coconut Mall.png" source="derivative">
    <format>PNG</format>
    <original>Mario Kart Wii Platinum Soundtrack [MP3]/10. Coconut Mall.mp3</original>
    <mtime>1636284921</mtime>
    <size>44519</size>
    <md5>e45b0d19bf94ddc74dd26131a2bd9bea</md5>
    <crc32>98f159db</crc32>
    <sha1>3d4ec2f35a9c8a583721253d59607362e8d3c60b</sha1>
  </file>
  <file name="Mario Kart Wii Platinum Soundtrack [MP3]/10. Coconut Mall_spectrogram.png" source="derivative">
    <format>Spectrogram</format>
    <original>Mario Kart Wii Platinum Soundtrack [MP3]/10. Coconut Mall.mp3</original>
    <mtime>1636291672</mtime>
    <size>319902</size>
    <md5>3ac4e56b496b789e0630fb8590decfc6</md5>
    <crc32>098655ce</crc32>
    <sha1>d32c3dc9ebbab4350794f0d147d097aa59d85720</sha1>
  </file>
  <file name="Mario Kart Wii Platinum Soundtrack [MP3]/11. DK Summit.afpk" source="derivative">
    <format>Columbia Peaks</format>
    <original>Mario Kart Wii Platinum Soundtrack [MP3]/11. DK Summit.mp3</original>
    <mtime>1636293926</mtime>
    <size>27864</size>
    <md5>b9d911375f80d15c745d1f13588edbde</md5>
    <crc32>22695090</crc32>
    <sha1>abbe8d430cfc61556d1c3b1258cde6d8c0f8d03e</sha1>
  </file>
  <file name="Mario Kart Wii Platinum Soundtrack [MP3]/11. DK Summit.mp3" source="original">
    <mtime>1636284185</mtime>
    <size>5617824</size>
    <md5>ea91578ba37b6692a42db362894ba42c</md5>
    <crc32>25d57414</crc32>
    <sha1>221b52f39cf8bd009a5f81bbea63874204d40b6f</sha1>
    <format>VBR MP3</format>
    <length>133.04</length>
    <title>DK Summit</title>
    <creator>Asuka Ohta, Ryo Nagamatsu</creator>
    <album>Mario Kart Wii Platinum Soundtrack</album>
    <track>11/43</track>
    <artist>Asuka Ohta, Ryo Nagamatsu</artist>
    <genre>Game Soundtrack</genre>
    <comment>http://sittingonclouds.net</comment>
  </file>
  <file name="Mario Kart Wii Platinum Soundtrack [MP3]/11. DK Summit.png" source="derivative">
    <format>PNG</format>
    <original>Mario Kart Wii Platinum Soundtrack [MP3]/11. DK Summit.mp3</original>
    <mtime>1636285727</mtime>
    <size>41215</size>
    <md5>437518384e4083036fcc28447aafecf4</md5>
    <crc32>c94e9842</crc32>
    <sha1>5d3cd7297f102b992d49cff292c100036ca42372</sha1>
  </file>
  <file name="Mario Kart Wii Platinum Soundtrack [MP3]/11. DK Summit_spectrogram.png" source="derivative">
    <format>Spectrogram</format>
    <original>Mario Kart Wii Platinum Soundtrack [MP3]/11. DK Summit.mp3</original>
    <mtime>1636291780</mtime>
    <size>301394</size>
    <md5>9ca64183a1dc2ac9c5d11bd89670ca05</md5>
    <crc32>0a177f7c</crc32>
    <sha1>a077d7e08c81bd6e914ad2e9054b6b2496ab81ab</sha1>
  </file>
  <file name="Mario Kart Wii Platinum Soundtrack [MP3]/12. Wario's Gold Mine.afpk" source="derivative">
    <format>Columbia Peaks</format>
    <original>Mario Kart Wii Platinum Soundtrack [MP3]/12. Wario's Gold Mine.mp3</original>
    <mtime>1636295943</mtime>
    <size>31568</size>
    <md5>088c707236603df8ce3ccfe3c49a826b</md5>
    <crc32>0e676755</crc32>
    <sha1>246777a9f69f86d0f033a51d4a20c259ac297ee4</sha1>
  </file>
  <file name="Mario Kart Wii Platinum Soundtrack [MP3]/12. Wario's Gold Mine.mp3" source="original">
    <mtime>1636284403</mtime>
    <size>5812191</size>
    <md5>d57406fd8a6fee9d73e41d718483d2b0</md5>
    <crc32>926f03b1</crc32>
    <sha1>150317a865b6135760fef5c347b0a19af326f141</sha1>
    <format>VBR MP3</format>
    <length>137.9</length>
    <title>Wario's Gold Mine</title>
    <creator>Asuka Ohta, Ryo Nagamatsu</creator>
    <album>Mario Kart Wii Platinum Soundtrack</album>
    <track>12/43</track>
    <artist>Asuka Ohta, Ryo Nagamatsu</artist>
    <genre>Game Soundtrack</genre>
    <comment>http://sittingonclouds.net</comment>
  </file>
  <file name="Mario Kart Wii Platinum Soundtrack [MP3]/12. Wario's Gold Mine.png" source="derivative">
    <format>PNG</format>
    <original>Mario Kart Wii Platinum Soundtrack [MP3]/12. Wario's Gold Mine.mp3</original>
    <mtime>1636286704</mtime>
    <size>45476</size>
    <md5>9f21a53e281b73e935ece63e64b8fbce</md5>
    <crc32>ef0ef987</crc32>
    <sha1>61d9d872773b5787f15be05b9778645b9c9b287d</sha1>
  </file>
  <file name="Mario Kart Wii Platinum Soundtrack [MP3]/12. Wario's Gold Mine_spectrogram.png" source="derivative">
    <format>Spectrogram</format>
    <original>Mario Kart Wii Platinum Soundtrack [MP3]/12. Wario's Gold Mine.mp3</original>
    <mtime>1636292003</mtime>
    <size>326514</size>
    <md5>79bb90a41fa9a6820e4fbbd96ea91174</md5>
    <crc32>3d3ae1ba</crc32>
    <sha1>b58e61954df07a43d677e284e33bc1568830ab65</sha1>
  </file>
  <file name="Mario Kart Wii Platinum Soundtrack [MP3]/13. Daisy Circuit.afpk" source="derivative">
    <format>Columbia Peaks</format>
    <original>Mario Kart Wii Platinum Soundtrack [MP3]/13. Daisy Circuit.mp3</original>
    <mtime>1636295165</mtime>
    <size>28864</size>
    <md5>ff68533abbaacb6681cccb5599be9f22</md5>
    <crc32>7dd958cd</crc32>
    <sha1>293a3e17b525f63f6dab80eeb32cc0def4b6d97b</sha1>
  </file>
  <file name="Mario Kart Wii Platinum Soundtrack [MP3]/13. Daisy Circuit.mp3" source="original">
    <mtime>1636284236</mtime>
    <size>5629326</size>
    <md5>725be6fb6711ad3413ca0989ee98a2d5</md5>
    <crc32>4fb277b6</crc32>
    <sha1>41d7ec7cc649dfe9a26a8630bc4904596cde7d81</sha1>
    <format>VBR MP3</format>
    <length>133.33</length>
    <title>Daisy Circuit</title>
    <creator>Asuka Ohta, Ryo Nagamatsu</creator>
    <album>Mario Kart Wii Platinum Soundtrack</album>
    <track>13/43</track>
    <artist>Asuka Ohta, Ryo Nagamatsu</artist>
    <genre>Game Soundtrack</genre>
    <comment>http://sittingonclouds.net</comment>
  </file>
  <file name="Mario Kart Wii Platinum Soundtrack [MP3]/13. Daisy Circuit.png" source="derivative">
    <format>PNG</format>
    <original>Mario Kart Wii Platinum Soundtrack [MP3]/13. Daisy Circuit.mp3</original>
    <mtime>1636286384</mtime>
    <size>44418</size>
    <md5>db06dc4f2e92e5138069a38fee67bcbd</md5>
    <crc32>032d7c25</crc32>
    <sha1>3fea052a9d6b40e410666120793735e8c8a574fa</sha1>
  </file>
  <file name="Mario Kart Wii Platinum Soundtrack [MP3]/13. Daisy Circuit_spectrogram.png" source="derivative">
    <format>Spectrogram</format>
    <original>Mario Kart Wii Platinum Soundtrack [MP3]/13. Daisy Circuit.mp3</original>
    <mtime>1636291493</mtime>
    <size>318382</size>
    <md5>8c0239670419059c7ea17c5a92b6e29b</md5>
    <crc32>14d12dcd</crc32>
    <sha1>a0b5c6ca19fae3195611873c5759ce3053a8388e</sha1>
  </file>
  <file name="Mario Kart Wii Platinum Soundtrack [MP3]/14. Koopa Cape.afpk" source="derivative">
    <format>Columbia Peaks</format>
    <original>Mario Kart Wii Platinum Soundtrack [MP3]/14. Koopa Cape.mp3</original>
    <mtime>1636295581</mtime>
    <size>27856</size>
    <md5>e755b46a3b1629c6b830b5f50a5539c7</md5>
    <crc32>d817b77a</crc32>
    <sha1>e2548b3533d45d991791454da4ca4948705cd20f</sha1>
  </file>
  <file name="Mario Kart Wii Platinum Soundtrack [MP3]/14. Koopa Cape.mp3" source="original">
    <mtime>1636284384</mtime>
    <size>5349287</size>
    <md5>bf7ccaa36cdba5909e6b856689bc8782</md5>
    <crc32>a5578ded</crc32>
    <sha1>072026a3617e413c706abdd7b9d67ae6c23adc1f</sha1>
    <format>VBR MP3</format>
    <length>126.33</length>
    <title>Koopa Cape</title>
    <creator>Asuka Ohta, Ryo Nagamatsu</creator>
    <album>Mario Kart Wii Platinum Soundtrack</album>
    <track>14/43</track>
    <artist>Asuka Ohta, Ryo Nagamatsu</artist>
    <genre>Game Soundtrack</genre>
    <comment>http://sittingonclouds.net</comment>
  </file>
  <file name="Mario Kart Wii Platinum Soundtrack [MP3]/14. Koopa Cape.png" source="derivative">
    <format>PNG</format>
    <original>Mario Kart Wii Platinum Soundtrack [MP3]/14. Koopa Cape.mp3</original>
    <mtime>1636286470</mtime>
    <size>41672</size>
    <md5>ac6dbc970cc80f625e5c6efe14585eca</md5>
    <crc32>04e7d820</crc32>
    <sha1>b7dd222ca998e4c8a5e3b0ae2b90eae9f348f1c4</sha1>
  </file>
  <file name="Mario Kart Wii Platinum Soundtrack [MP3]/14. Koopa Cape_spectrogram.png" source="derivative">
    <format>Spectrogram</format>
    <original>Mario Kart Wii Platinum Soundtrack [MP3]/14. Koopa Cape.mp3</original>
    <mtime>1636288235</mtime>
    <size>340863</size>
    <md5>ded01f1ea0a0d802a0de695572a82457</md5>
    <crc32>16643e70</crc32>
    <sha1>254c4f19c730e29b4966687d5d8bebeca1d0150a</sha1>
  </file>
  <file name="Mario Kart Wii Platinum Soundtrack [MP3]/15. Maple Treeway.afpk" source="derivative">
    <format>Columbia Peaks</format>
    <original>Mario Kart Wii Platinum Soundtrack [MP3]/15. Maple Treeway.mp3</original>
    <mtime>1636295740</mtime>
    <size>31200</size>
    <md5>ff789db85ec2913fbf7bb73cbea10546</md5>
    <crc32>96e1e96c</crc32>
    <sha1>9f0bd08dd417c02dd0449f53133df948f8ae6927</sha1>
  </file>
  <file name="Mario Kart Wii Platinum Soundtrack [MP3]/15. Maple Treeway.mp3" source="original">
    <mtime>1636284318</mtime>
    <size>5984591</size>
    <md5>4d33cffb95d0e0bdc1ddf3caeacde611</md5>
    <crc32>a2b2bb29</crc32>
    <sha1>223e2f4bec6265eda5e05b7503c97763f5b702c3</sha1>
    <format>VBR MP3</format>
    <length>142.21</length>
    <title>Maple Treeway</title>
    <creator>Asuka Ohta, Ryo Nagamatsu</creator>
    <album>Mario Kart Wii Platinum Soundtrack</album>
    <track>15/43</track>
    <artist>Asuka Ohta, Ryo Nagamatsu</artist>
    <genre>Game Soundtrack</genre>
    <comment>http://sittingonclouds.net</comment>
  </file>
  <file name="Mario Kart Wii Platinum Soundtrack [MP3]/15. Maple Treeway.png" source="derivative">
    <format>PNG</format>
    <original>Mario Kart Wii Platinum Soundtrack [MP3]/15. Maple Treeway.mp3</original>
    <mtime>1636286559</mtime>
    <size>43702</size>
    <md5>3e314728f81b8189ccac9ae68ba5fb61</md5>
    <crc32>8db6240a</crc32>
    <sha1>2964d60332d4d977b75d2e002cf33278b3584fdd</sha1>
  </file>
  <file name="Mario Kart Wii Platinum Soundtrack [MP3]/15. Maple Treeway_spectrogram.png" source="derivative">
    <format>Spectrogram</format>
    <original>Mario Kart Wii Platinum Soundtrack [MP3]/15. Maple Treeway.mp3</original>
    <mtime>1636288500</mtime>
    <size>317878</size>
    <md5>7ef967c257c488765722c12dd2b5452e</md5>
    <crc32>1c4f04c5</crc32>
    <sha1>6c96062ec63848e39415b8d4d7e757f24ccc5e34</sha1>
  </file>
  <file name="Mario Kart Wii Platinum Soundtrack [MP3]/16. Grumble Volcano.afpk" source="derivative">
    <format>Columbia Peaks</format>
    <original>Mario Kart Wii Platinum Soundtrack [MP3]/16. Grumble Volcano.mp3</original>
    <mtime>1636294610</mtime>
    <size>33768</size>
    <md5>51093493fc95061cd8a17526b8695001</md5>
    <crc32>81466325</crc32>
    <sha1>eb04dac783b2856ec24071214cb18da22cc59388</sha1>
  </file>
  <file name="Mario Kart Wii Platinum Soundtrack [MP3]/16. Grumble Volcano.mp3" source="original">
    <mtime>1636284273</mtime>
    <size>6591681</size>
    <md5>dc920cba4897ed90538ced39fb9968f0</md5>
    <crc32>3a8fcc0e</crc32>
    <sha1>a077efd9585b475665cf448ae34a83271c07ee7a</sha1>
    <format>VBR MP3</format>
    <length>157.39</length>
    <title>Grumble Volcano</title>
    <creator>Asuka Ohta, Ryo Nagamatsu</creator>
    <album>Mario Kart Wii Platinum Soundtrack</album>
    <track>16/43</track>
    <artist>Asuka Ohta, Ryo Nagamatsu</artist>
    <genre>Game Soundtrack</genre>
    <comment>http://sittingonclouds.net</comment>
  </file>
  <file name="Mario Kart Wii Platinum Soundtrack [MP3]/16. Grumble Volcano.png" source="derivative">
    <format>PNG</format>
    <original>Mario Kart Wii Platinum Soundtrack [MP3]/16. Grumble Volcano.mp3</original>
    <mtime>1636288059</mtime>
    <size>36050</size>
    <md5>4f25b2f162bc1682e65629286b0d3edd</md5>
    <crc32>e58f133d</crc32>
    <sha1>81218b632383a6dfb640d76044c39f799e3dc0f9</sha1>
  </file>
  <file name="Mario Kart Wii Platinum Soundtrack [MP3]/16. Grumble Volcano_spectrogram.png" source="derivative">
    <format>Spectrogram</format>
    <original>Mario Kart Wii Platinum Soundtrack [MP3]/16. Grumble Volcano.mp3</original>
    <mtime>1636288851</mtime>
    <size>302898</size>
    <md5>1af1749847e43ed2c61befee40ebb16b</md5>
    <crc32>b8160730</crc32>
    <sha1>855c2598664b9fb647bfa5117b83352f2c583e4b</sha1>
  </file>
  <file name="Mario Kart Wii Platinum Soundtrack [MP3]/17. Dry Dry Ruins.afpk" source="derivative">
    <format>Columbia Peaks</format>
    <original>Mario Kart Wii Platinum Soundtrack [MP3]/17. Dry Dry Ruins.mp3</original>
    <mtime>1636294342</mtime>
    <size>29256</size>
    <md5>53d7cd829602d2e613cddc8092a816b9</md5>
    <crc32>32fa35d3</crc32>
    <sha1>d0f0f06c0861d800fb2b27b3f5262f88d3a981f3</sha1>
  </file>
  <file name="Mario Kart Wii Platinum Soundtrack [MP3]/17. Dry Dry Ruins.mp3" source="original">
    <mtime>1636284210</mtime>
    <size>5835171</size>
    <md5>fb1689ffdd6dfdf9168534ad08a2ed7a</md5>
    <crc32>c92209ba</crc32>
    <sha1>43bfd6b743d79dd7974df526e561147f1a288e76</sha1>
    <format>VBR MP3</format>
    <length>138.48</length>
    <title>Dry Dry Ruins</title>
    <creator>Asuka Ohta, Ryo Nagamatsu</creator>
    <album>Mario Kart Wii Platinum Soundtrack</album>
    <track>17/43</track>
    <artist>Asuka Ohta, Ryo Nagamatsu</artist>
    <genre>Game Soundtrack</genre>
    <comment>http://sittingonclouds.net</comment>
  </file>
  <file name="Mario Kart Wii Platinum Soundtrack [MP3]/17. Dry Dry Ruins.png" source="derivative">
    <format>PNG</format>
    <original>Mario Kart Wii Platinum Soundtrack [MP3]/17. Dry Dry Ruins.mp3</original>
    <mtime>1636286949</mtime>
    <size>38308</size>
    <md5>906cce722969c9ca0dd954a5c342c5ce</md5>
    <crc32>675d9d35</crc32>
    <sha1>109537f22e6603c63fd59d33f793088ef19d0b93</sha1>
  </file>
  <file name="Mario Kart Wii Platinum Soundtrack [MP3]/17. Dry Dry Ruins_spectrogram.png" source="derivative">
    <format>Spectrogram</format>
    <original>Mario Kart Wii Platinum Soundtrack [MP3]/17. Dry Dry Ruins.mp3</original>
    <mtime>1636288557</mtime>
    <size>324404</size>
    <md5>f1f0a3035a640570fb1524242717ff86</md5>
    <crc32>54728484</crc32>
    <sha1>cd1a6179ca5702d981fa79e1921ac3b5fac3502c</sha1>
  </file>
  <file name="Mario Kart Wii Platinum Soundtrack [MP3]/18. Moonview Highway.afpk" source="derivative">
    <format>Columbia Peaks</format>
    <original>Mario Kart Wii Platinum Soundtrack [MP3]/18. Moonview Highway.mp3</original>
    <mtime>1636294114</mtime>
    <size>28704</size>
    <md5>10fafc5a10d56bc4f92bdca17eba3e81</md5>
    <crc32>f8549f12</crc32>
    <sha1>c8d53223129ab5209b43097b714882d58816f042</sha1>
  </file>
  <file name="Mario Kart Wii Platinum Soundtrack [MP3]/18. Moonview Highway.mp3" source="original">
    <mtime>1636284366</mtime>
    <size>5257348</size>
    <md5>03566f2383b5979a61b9e60c0286243b</md5>
    <crc32>fb550849</crc32>
    <sha1>501c7047548704ca35e7b44d3912d2ea5e8633e8</sha1>
    <format>VBR MP3</format>
    <length>124.03</length>
    <title>Moonview Highway</title>
    <creator>Asuka Ohta, Ryo Nagamatsu</creator>
    <album>Mario Kart Wii Platinum Soundtrack</album>
    <track>18/43</track>
    <artist>Asuka Ohta, Ryo Nagamatsu</artist>
    <genre>Game Soundtrack</genre>
    <comment>http://sittingonclouds.net</comment>
  </file>
  <file name="Mario Kart Wii Platinum Soundtrack [MP3]/18. Moonview Highway.png" source="derivative">
    <format>PNG</format>
    <original>Mario Kart Wii Platinum Soundtrack [MP3]/18. Moonview Highway.mp3</original>
    <mtime>1636287694</mtime>
    <size>43188</size>
    <md5>7eb606f4b8203b0f687769af4ace5f07</md5>
    <crc32>1b0b59d5</crc32>
    <sha1>717431e30aa61d25af09526cc036a476e9f70888</sha1>
  </file>
  <file name="Mario Kart Wii Platinum Soundtrack [MP3]/18. Moonview Highway_spectrogram.png" source="derivative">
    <format>Spectrogram</format>
    <original>Mario Kart Wii Platinum Soundtrack [MP3]/18. Moonview Highway.mp3</original>
    <mtime>1636288426</mtime>
    <size>321260</size>
    <md5>60ff3c1d28ab16bdbeb8460719a90ca1</md5>
    <crc32>fe8acaa5</crc32>
    <sha1>f9b719085907e960de456f86058248c897831362</sha1>
  </file>
  <file name="Mario Kart Wii Platinum Soundtrack [MP3]/19. Bowser's Castle.afpk" source="derivative">
    <format>Columbia Peaks</format>
    <original>Mario Kart Wii Platinum Soundtrack [MP3]/19. Bowser's Castle.mp3</original>
    <mtime>1636293495</mtime>
    <size>34584</size>
    <md5>373bb610f810d705783f330fd5a07723</md5>
    <crc32>26545c7a</crc32>
    <sha1>fd498fcea90ba5619642519c10ef672d46dfb8f5</sha1>
  </file>
  <file name="Mario Kart Wii Platinum Soundtrack [MP3]/19. Bowser's Castle.mp3" source="original">
    <mtime>1636284196</mtime>
    <size>6888432</size>
    <md5>c324a240508a2ba41f69451005bee549</md5>
    <crc32>7a694d68</crc32>
    <sha1>35de201182a92b6ab508c67c1729925069ef2a2f</sha1>
    <format>VBR MP3</format>
    <length>164.81</length>
    <title>Bowser's Castle</title>
    <creator>Asuka Ohta, Ryo Nagamatsu</creator>
    <album>Mario Kart Wii Platinum Soundtrack</album>
    <track>19/43</track>
    <artist>Asuka Ohta, Ryo Nagamatsu</artist>
    <genre>Game Soundtrack</genre>
    <comment>http://sittingonclouds.net</comment>
  </file>
  <file name="Mario Kart Wii Platinum Soundtrack [MP3]/19. Bowser's Castle.png" source="derivative">
    <format>PNG</format>
    <original>Mario Kart Wii Platinum Soundtrack [MP3]/19. Bowser's Castle.mp3</original>
    <mtime>1636287616</mtime>
    <size>40279</size>
    <md5>6dd4a88171a859d44c182cd6f7be43cb</md5>
    <crc32>ccfb6f88</crc32>
    <sha1>da9225d0ecddf5bd0cdc0e4197409f39e533d9e0</sha1>
  </file>
  <file name="Mario Kart Wii Platinum Soundtrack [MP3]/19. Bowser's Castle_spectrogram.png" source="derivative">
    <format>Spectrogram</format>
    <original>Mario Kart Wii Platinum Soundtrack [MP3]/19. Bowser's Castle.mp3</original>
    <mtime>1636288334</mtime>
    <size>325616</size>
    <md5>42ecb498a1fae3efa568a61be8aa774b</md5>
    <crc32>7d8384ff</crc32>
    <sha1>770668ae53909d8d8274fa05860a44786d229258</sha1>
  </file>
  <file name="Mario Kart Wii Platinum Soundtrack [MP3]/20. Rainbow Road.afpk" source="derivative">
    <format>Columbia Peaks</format>
    <original>Mario Kart Wii Platinum Soundtrack [MP3]/20. Rainbow Road.mp3</original>
    <mtime>1636293210</mtime>
    <size>25688</size>
    <md5>610bd599beacd0b5ce9142f5e7674d1e</md5>
    <crc32>db7783c1</crc32>
    <sha1>cef659ad00ad7d8d2c0dffb855f765179309e02a</sha1>
  </file>
  <file name="Mario Kart Wii Platinum Soundtrack [MP3]/20. Rainbow Road.mp3" source="original">
    <mtime>1636284155</mtime>
    <size>7012769</size>
    <md5>a90fd7d008c09900e5ad321b12c9d675</md5>
    <crc32>0baee336</crc32>
    <sha1>bae2a7e1924e0d270eb6a8d16b95edbf2ad92d29</sha1>
    <format>VBR MP3</format>
    <length>167.92</length>
    <title>Rainbow Road</title>
    <creator>Asuka Ohta, Ryo Nagamatsu</creator>
    <album>Mario Kart Wii Platinum Soundtrack</album>
    <track>20/43</track>
    <artist>Asuka Ohta, Ryo Nagamatsu</artist>
    <genre>Game Soundtrack</genre>
    <comment>http://sittingonclouds.net</comment>
  </file>
  <file name="Mario Kart Wii Platinum Soundtrack [MP3]/20. Rainbow Road.png" source="derivative">
    <format>PNG</format>
    <original>Mario Kart Wii Platinum Soundtrack [MP3]/20. Rainbow Road.mp3</original>
    <mtime>1636285072</mtime>
    <size>40119</size>
    <md5>67224d7992091d529ce1a6df00289651</md5>
    <crc32>1d859575</crc32>
    <sha1>c3a4f7bbdbf1f4512429b6b9d59592da7c077240</sha1>
  </file>
  <file name="Mario Kart Wii Platinum Soundtrack [MP3]/20. Rainbow Road_spectrogram.png" source="derivative">
    <format>Spectrogram</format>
    <original>Mario Kart Wii Platinum Soundtrack [MP3]/20. Rainbow Road.mp3</original>
    <mtime>1636290132</mtime>
    <size>280396</size>
    <md5>21e05dc92e25988fc997b492016442ae</md5>
    <crc32>6809b321</crc32>
    <sha1>afd87f3b3ca4ef682004c0cfd00fbf2298cc5a46</sha1>
  </file>
  <file name="Mario Kart Wii Platinum Soundtrack [MP3]/21. 1st Place Fanfare (Grand Prix &amp; VS).afpk" source="derivative">
    <format>Columbia Peaks</format>
    <original>Mario Kart Wii Platinum Soundtrack [MP3]/21. 1st Place Fanfare (Grand Prix &amp; VS).mp3</original>
    <mtime>1636293132</mtime>
    <size>1280</size>
    <md5>69bb92f070b5d724721dae2c9b52068b</md5>
    <crc32>2234f0f4</crc32>
    <sha1>9bb0cf44d14ccf5984bdde39f82dd36cc698726c</sha1>
  </file>
  <file name="Mario Kart Wii Platinum Soundtrack [MP3]/21. 1st Place Fanfare (Grand Prix &amp; VS).mp3" source="original">
    <mtime>1636284371</mtime>
    <size>580423</size>
    <md5>be456e7494ac74aed1fcfbf65ec1f3da</md5>
    <crc32>cf2d5c88</crc32>
    <sha1>391750112b2ad31b2bddf2afc444e6fced9c2a86</sha1>
    <format>VBR MP3</format>
    <length>7.11</length>
    <title>1st Place Fanfare (Grand Prix &amp; VS)</title>
    <creator>Asuka Ohta, Ryo Nagamatsu</creator>
    <album>Mario Kart Wii Platinum Soundtrack</album>
    <track>21/43</track>
    <artist>Asuka Ohta, Ryo Nagamatsu</artist>
    <genre>Game Soundtrack</genre>
    <comment>http://sittingonclouds.net</comment>
  </file>
  <file name="Mario Kart Wii Platinum Soundtrack [MP3]/21. 1st Place Fanfare (Grand Prix &amp; VS).png" source="derivative">
    <format>PNG</format>
    <original>Mario Kart Wii Platinum Soundtrack [MP3]/21. 1st Place Fanfare (Grand Prix &amp; VS).mp3</original>
    <mtime>1636286818</mtime>
    <size>27376</size>
    <md5>2eeffc274becb5ec3497fe04e1156cb4</md5>
    <crc32>eea2484d</crc32>
    <sha1>db8879e36e8ea1cd8433e454429d1298459e2f41</sha1>
  </file>
  <file name="Mario Kart Wii Platinum Soundtrack [MP3]/21. 1st Place Fanfare (Grand Prix &amp; VS)_spectrogram.png" source="derivative">
    <format>Spectrogram</format>
    <original>Mario Kart Wii Platinum Soundtrack [MP3]/21. 1st Place Fanfare (Grand Prix &amp; VS).mp3</original>
    <mtime>1636290230</mtime>
    <size>279859</size>
    <md5>1457dbb29a057610cd7b02a05440b102</md5>
    <crc32>7b53f136</crc32>
    <sha1>97f0426bfa1c35a2aac6b98558dc701528957784</sha1>
  </file>
  <file name="Mario Kart Wii Platinum Soundtrack [MP3]/22. High Placement Fanfare (Grand Prix &amp; VS).afpk" source="derivative">
    <format>Columbia Peaks</format>
    <original>Mario Kart Wii Platinum Soundtrack [MP3]/22. High Placement Fanfare (Grand Prix &amp; VS).mp3</original>
    <mtime>1636295646</mtime>
    <size>1408</size>
    <md5>d17c36aba427022fc5413bc4c6986bf3</md5>
    <crc32>050076f2</crc32>
    <sha1>f43b6cb7544f749126fe6ea34bfc1d739d551480</sha1>
  </file>
  <file name="Mario Kart Wii Platinum Soundtrack [MP3]/22. High Placement Fanfare (Grand Prix &amp; VS).mp3" source="original">
    <mtime>1636284333</mtime>
    <size>613870</size>
    <md5>00c9598c243db1be50399a0acd581715</md5>
    <crc32>be30b91a</crc32>
    <sha1>3d6d7c46f1770234239eb8690e07c7e69d30f0d3</sha1>
    <format>VBR MP3</format>
    <length>7.94</length>
    <title>High Placement Fanfare (Grand Prix &amp; VS)</title>
    <creator>Asuka Ohta, Ryo Nagamatsu</creator>
    <album>Mario Kart Wii Platinum Soundtrack</album>
    <track>22/43</track>
    <artist>Asuka Ohta, Ryo Nagamatsu</artist>
    <genre>Game Soundtrack</genre>
    <comment>http://sittingonclouds.net</comment>
  </file>
  <file name="Mario Kart Wii Platinum Soundtrack [MP3]/22. High Placement Fanfare (Grand Prix &amp; VS).png" source="derivative">
    <format>PNG</format>
    <original>Mario Kart Wii Platinum Soundtrack [MP3]/22. High Placement Fanfare (Grand Prix &amp; VS).mp3</original>
    <mtime>1636287487</mtime>
    <size>24428</size>
    <md5>873503de85689949a42a727ba34df99b</md5>
    <crc32>31a0e780</crc32>
    <sha1>f97d63b6428b34cd414da79dd10faa4ae5022a04</sha1>
  </file>
  <file name="Mario Kart Wii Platinum Soundtrack [MP3]/22. High Placement Fanfare (Grand Prix &amp; VS)_spectrogram.png" source="derivative">
    <format>Spectrogram</format>
    <original>Mario Kart Wii Platinum Soundtrack [MP3]/22. High Placement Fanfare (Grand Prix &amp; VS).mp3</original>
    <mtime>1636292083</mtime>
    <size>330629</size>
    <md5>3299ee660f4159a4533c923e4c334428</md5>
    <crc32>fbe46f88</crc32>
    <sha1>c0e8aeff2ba52d6612e7e4c8a2c876c700b10013</sha1>
  </file>
  <file name="Mario Kart Wii Platinum Soundtrack [MP3]/23. High Placement Results (Grand Prix &amp; VS).afpk" source="derivative">
    <format>Columbia Peaks</format>
    <original>Mario Kart Wii Platinum Soundtrack [MP3]/23. High Placement Results (Grand Prix &amp; VS).mp3</original>
    <mtime>1636295824</mtime>
    <size>10728</size>
    <md5>f866673a22c551a187f995ef6bfc7ade</md5>
    <crc32>38cefbe4</crc32>
    <sha1>2b332be459862c20d75b2073af721a80fd89e384</sha1>
  </file>
  <file name="Mario Kart Wii Platinum Soundtrack [MP3]/23. High Placement Results (Grand Prix &amp; VS).mp3" source="original">
    <mtime>1636284388</mtime>
    <size>2450800</size>
    <md5>f053dc0de9c2f1e32c15fb4babf6581e</md5>
    <crc32>e0543140</crc32>
    <sha1>18f9f9f58064eb49f87faa75ca509fd403bb50db</sha1>
    <format>VBR MP3</format>
    <length>53.86</length>
    <title>High Placement Results (Grand Prix &amp; VS)</title>
    <creator>Asuka Ohta, Ryo Nagamatsu</creator>
    <album>Mario Kart Wii Platinum Soundtrack</album>
    <track>23/43</track>
    <artist>Asuka Ohta, Ryo Nagamatsu</artist>
    <genre>Game Soundtrack</genre>
    <comment>http://sittingonclouds.net</comment>
  </file>
  <file name="Mario Kart Wii Platinum Soundtrack [MP3]/23. High Placement Results (Grand Prix &amp; VS).png" source="derivative">
    <format>PNG</format>
    <original>Mario Kart Wii Platinum Soundtrack [MP3]/23. High Placement Results (Grand Prix &amp; VS).mp3</original>
    <mtime>1636285663</mtime>
    <size>32304</size>
    <md5>dd98112783ff319326b5a188b4ef31bd</md5>
    <crc32>4995c917</crc32>
    <sha1>ac75810bf11ae333dffae6767ca0bf5c5f306f6f</sha1>
  </file>
  <file name="Mario Kart Wii Platinum Soundtrack [MP3]/23. High Placement Results (Grand Prix &amp; VS)_spectrogram.png" source="derivative">
    <format>Spectrogram</format>
    <original>Mario Kart Wii Platinum Soundtrack [MP3]/23. High Placement Results (Grand Prix &amp; VS).mp3</original>
    <mtime>1636288676</mtime>
    <size>355117</size>
    <md5>f33ab7fba56914d8f46acdaf109c80aa</md5>
    <crc32>fc88c77e</crc32>
    <sha1>c4399bacc87dc1a50f825411dbdabe11dcd65a1e</sha1>
  </file>
  <file name="Mario Kart Wii Platinum Soundtrack [MP3]/24. Low Placement Fanfare (Grand Prix &amp; VS).afpk" source="derivative">
    <format>Columbia Peaks</format>
    <original>Mario Kart Wii Platinum Soundtrack [MP3]/24. Low Placement Fanfare (Grand Prix &amp; VS).mp3</original>
    <mtime>1636295518</mtime>
    <size>1824</size>
    <md5>9a387af34f13b9216f743b8921e1f8c2</md5>
    <crc32>956a8bc9</crc32>
    <sha1>8bb992f3e3007d71742b006406e50d4d79df1497</sha1>
  </file>
  <file name="Mario Kart Wii Platinum Soundtrack [MP3]/24. Low Placement Fanfare (Grand Prix &amp; VS).mp3" source="original">
    <mtime>1636284162</mtime>
    <size>657753</size>
    <md5>d1651ef3e34f4a10422ca08f8dbe9636</md5>
    <crc32>ecef6643</crc32>
    <sha1>c46eb6289252bfb4fb8c4002b8d2bad162cea381</sha1>
    <format>VBR MP3</format>
    <length>9.04</length>
    <title>Low Placement Fanfare (Grand Prix &amp; VS)</title>
    <creator>Asuka Ohta, Ryo Nagamatsu</creator>
    <album>Mario Kart Wii Platinum Soundtrack</album>
    <track>24/43</track>
    <artist>Asuka Ohta, Ryo Nagamatsu</artist>
    <genre>Game Soundtrack</genre>
    <comment>http://sittingonclouds.net</comment>
  </file>
  <file name="Mario Kart Wii Platinum Soundtrack [MP3]/24. Low Placement Fanfare (Grand Prix &amp; VS).png" source="derivative">
    <format>PNG</format>
    <original>Mario Kart Wii Platinum Soundtrack [MP3]/24. Low Placement Fanfare (Grand Prix &amp; VS).mp3</original>
    <mtime>1636287326</mtime>
    <size>27096</size>
    <md5>c638219531238bf564141a69c7044ecd</md5>
    <crc32>5afe08f8</crc32>
    <sha1>825a37aad4ff42f6d04068fe3b497dfbc26a365e</sha1>
  </file>
  <file name="Mario Kart Wii Platinum Soundtrack [MP3]/24. Low Placement Fanfare (Grand Prix &amp; VS)_spectrogram.png" source="derivative">
    <format>Spectrogram</format>
    <original>Mario Kart Wii Platinum Soundtrack [MP3]/24. Low Placement Fanfare (Grand Prix &amp; VS).mp3</original>
    <mtime>1636291936</mtime>
    <size>340332</size>
    <md5>2b88be5e865d0fe475bb2942ccc7c8ec</md5>
    <crc32>f69245fd</crc32>
    <sha1>a521bcfdb8c4617aaa5f701401ab6fdce7f1ac47</sha1>
  </file>
  <file name="Mario Kart Wii Platinum Soundtrack [MP3]/25. Low Placement Results.afpk" source="derivative">
    <format>Columbia Peaks</format>
    <original>Mario Kart Wii Platinum Soundtrack [MP3]/25. Low Placement Results.mp3</original>
    <mtime>1636295340</mtime>
    <size>8168</size>
    <md5>b8e2efb6810e125c9d1769669c9096fb</md5>
    <crc32>2b19da09</crc32>
    <sha1>13b90753232917aefaf2a67f4c09073ef07de9c7</sha1>
  </file>
  <file name="Mario Kart Wii Platinum Soundtrack [MP3]/25. Low Placement Results.mp3" source="original">
    <mtime>1636284213</mtime>
    <size>2019219</size>
    <md5>82af14896f088280c0c64927047afea0</md5>
    <crc32>4b8005f5</crc32>
    <sha1>dd11fe219882163d23f5b076a98de2c799915ce8</sha1>
    <format>VBR MP3</format>
    <length>43.08</length>
    <title>Low Placement Results</title>
    <creator>Asuka Ohta, Ryo Nagamatsu</creator>
    <album>Mario Kart Wii Platinum Soundtrack</album>
    <track>25/43</track>
    <artist>Asuka Ohta, Ryo Nagamatsu</artist>
    <genre>Game Soundtrack</genre>
    <comment>http://sittingonclouds.net</comment>
  </file>
  <file name="Mario Kart Wii Platinum Soundtrack [MP3]/25. Low Placement Results.png" source="derivative">
    <format>PNG</format>
    <original>Mario Kart Wii Platinum Soundtrack [MP3]/25. Low Placement Results.mp3</original>
    <mtime>1636287269</mtime>
    <size>29806</size>
    <md5>60fc7ded492d821371596060b85e43dd</md5>
    <crc32>fed3d6d6</crc32>
    <sha1>d4c7f0ca0824b71f1712f08ced4c68cbc7f12cf3</sha1>
  </file>
  <file name="Mario Kart Wii Platinum Soundtrack [MP3]/25. Low Placement Results_spectrogram.png" source="derivative">
    <format>Spectrogram</format>
    <original>Mario Kart Wii Platinum Soundtrack [MP3]/25. Low Placement Results.mp3</original>
    <mtime>1636291712</mtime>
    <size>345795</size>
    <md5>7646488013be9902c257b511947586af</md5>
    <crc32>693ff2ce</crc32>
    <sha1>d186a8144d2b2c5650e8bf20fb0a19eee4360191</sha1>
  </file>
  <file name="Mario Kart Wii Platinum Soundtrack [MP3]/26. Block Plaza.afpk" source="derivative">
    <format>Columbia Peaks</format>
    <original>Mario Kart Wii Platinum Soundtrack [MP3]/26. Block Plaza.mp3</original>
    <mtime>1636294944</mtime>
    <size>30960</size>
    <md5>4284c321f62413921795d9ee4cf8919f</md5>
    <crc32>476e3f15</crc32>
    <sha1>740a9e0c3630fe95ff7b4ae74eb2ca224c61a697</sha1>
  </file>
  <file name="Mario Kart Wii Platinum Soundtrack [MP3]/26. Block Plaza.mp3" source="original">
    <mtime>1636284243</mtime>
    <size>5108963</size>
    <md5>b7723b6d06fefaa1e7468033c724c724</md5>
    <crc32>4770a53e</crc32>
    <sha1>9f3133d9e5bb534603a33e8b403cc054cd320385</sha1>
    <format>VBR MP3</format>
    <length>120.32</length>
    <title>Block Plaza</title>
    <creator>Asuka Ohta, Ryo Nagamatsu</creator>
    <album>Mario Kart Wii Platinum Soundtrack</album>
    <track>26/43</track>
    <artist>Asuka Ohta, Ryo Nagamatsu</artist>
    <genre>Game Soundtrack</genre>
    <comment>http://sittingonclouds.net</comment>
  </file>
  <file name="Mario Kart Wii Platinum Soundtrack [MP3]/26. Block Plaza.png" source="derivative">
    <format>PNG</format>
    <original>Mario Kart Wii Platinum Soundtrack [MP3]/26. Block Plaza.mp3</original>
    <mtime>1636287184</mtime>
    <size>46827</size>
    <md5>f22542d263e30f2b08a3d3bffc410330</md5>
    <crc32>e7f30a36</crc32>
    <sha1>d0c1cf4a3a26916662623674bd1c1a52a956dc60</sha1>
  </file>
  <file name="Mario Kart Wii Platinum Soundtrack [MP3]/26. Block Plaza_spectrogram.png" source="derivative">
    <format>Spectrogram</format>
    <original>Mario Kart Wii Platinum Soundtrack [MP3]/26. Block Plaza.mp3</original>
    <mtime>1636291610</mtime>
    <size>319712</size>
    <md5>ad8ca71416162aadbf87517e347239bc</md5>
    <crc32>8bffde06</crc32>
    <sha1>8d35e359f8aa367ca77b2eb50fe5ab34acbc423d</sha1>
  </file>
  <file name="Mario Kart Wii Platinum Soundtrack [MP3]/27. Delfino Pier.afpk" source="derivative">
    <format>Columbia Peaks</format>
    <original>Mario Kart Wii Platinum Soundtrack [MP3]/27. Delfino Pier.mp3</original>
    <mtime>1636292548</mtime>
    <size>34816</size>
    <md5>480757fd6a4fb23d3299675a8b2f51a3</md5>
    <crc32>b36fe41a</crc32>
    <sha1>803a03618b8ac8149d117eba48871f32f94c4636</sha1>
  </file>
  <file name="Mario Kart Wii Platinum Soundtrack [MP3]/27. Delfino Pier.mp3" source="original">
    <mtime>1636284352</mtime>
    <size>5934434</size>
    <md5>cbb2bb61d08484b0d36de3174c0c6dcd</md5>
    <crc32>811c9155</crc32>
    <sha1>b4e4693da27f99ef124506d0aba0d7bc75d81731</sha1>
    <format>VBR MP3</format>
    <length>140.96</length>
    <title>Delfino Pier</title>
    <creator>Asuka Ohta, Ryo Nagamatsu</creator>
    <album>Mario Kart Wii Platinum Soundtrack</album>
    <track>27/43</track>
    <artist>Asuka Ohta, Ryo Nagamatsu</artist>
    <genre>Game Soundtrack</genre>
    <comment>http://sittingonclouds.net</comment>
  </file>
  <file name="Mario Kart Wii Platinum Soundtrack [MP3]/27. Delfino Pier.png" source="derivative">
    <format>PNG</format>
    <original>Mario Kart Wii Platinum Soundtrack [MP3]/27. Delfino Pier.mp3</original>
    <mtime>1636287096</mtime>
    <size>47475</size>
    <md5>7f2848bbe07e7f1020d3177768d8ecde</md5>
    <crc32>8dcf4778</crc32>
    <sha1>1b83304256e0a0a91e472abfad4fcd002f5acc26</sha1>
  </file>
  <file name="Mario Kart Wii Platinum Soundtrack [MP3]/27. Delfino Pier_spectrogram.png" source="derivative">
    <format>Spectrogram</format>
    <original>Mario Kart Wii Platinum Soundtrack [MP3]/27. Delfino Pier.mp3</original>
    <mtime>1636290337</mtime>
    <size>319545</size>
    <md5>d139b7124b4046b06680a715cebaf796</md5>
    <crc32>4f165205</crc32>
    <sha1>ba78b1da37c74301655f0dec5382c328818dc972</sha1>
  </file>
  <file name="Mario Kart Wii Platinum Soundtrack [MP3]/28. Funky Stadium.afpk" source="derivative">
    <format>Columbia Peaks</format>
    <original>Mario Kart Wii Platinum Soundtrack [MP3]/28. Funky Stadium.mp3</original>
    <mtime>1636292686</mtime>
    <size>28856</size>
    <md5>57af2030a3a419e7957de4d52fd66e1d</md5>
    <crc32>59a61dee</crc32>
    <sha1>dbee25d32fd94682aecde6f3ee880b426c6eb153</sha1>
  </file>
  <file name="Mario Kart Wii Platinum Soundtrack [MP3]/28. Funky Stadium.mp3" source="original">
    <mtime>1636284174</mtime>
    <size>4633538</size>
    <md5>aee5a102534a7629831f35edc9d4e736</md5>
    <crc32>64e68325</crc32>
    <sha1>772b0dadcf1d65fc2ed3c0b29b5e47ad8c2f21d9</sha1>
    <format>VBR MP3</format>
    <length>108.43</length>
    <title>Funky Stadium</title>
    <creator>Asuka Ohta, Ryo Nagamatsu</creator>
    <album>Mario Kart Wii Platinum Soundtrack</album>
    <track>28/43</track>
    <artist>Asuka Ohta, Ryo Nagamatsu</artist>
    <genre>Game Soundtrack</genre>
    <comment>http://sittingonclouds.net</comment>
  </file>
  <file name="Mario Kart Wii Platinum Soundtrack [MP3]/28. Funky Stadium.png" source="derivative">
    <format>PNG</format>
    <original>Mario Kart Wii Platinum Soundtrack [MP3]/28. Funky Stadium.mp3</original>
    <mtime>1636287021</mtime>
    <size>40099</size>
    <md5>006ed0e47d9283f56108707616438adf</md5>
    <crc32>d69e4284</crc32>
    <sha1>29c9b1954dab309f7d9d26f1d06a99d62b99455c</sha1>
  </file>
  <file name="Mario Kart Wii Platinum Soundtrack [MP3]/28. Funky Stadium_spectrogram.png" source="derivative">
    <format>Spectrogram</format>
    <original>Mario Kart Wii Platinum Soundtrack [MP3]/28. Funky Stadium.mp3</original>
    <mtime>1636291412</mtime>
    <size>336082</size>
    <md5>eb96860134d2d8c270866ab0759dc170</md5>
    <crc32>67015cb7</crc32>
    <sha1>7ad1cd5c28c21bfcf0a1234e1bc995fc2e337404</sha1>
  </file>
  <file name="Mario Kart Wii Platinum Soundtrack [MP3]/29. Chain Chomp Wheel.afpk" source="derivative">
    <format>Columbia Peaks</format>
    <original>Mario Kart Wii Platinum Soundtrack [MP3]/29. Chain Chomp Wheel.mp3</original>
    <mtime>1636294475</mtime>
    <size>30808</size>
    <md5>f80a5b6ef97cd8b5a911f375965f953e</md5>
    <crc32>6fc8a756</crc32>
    <sha1>324ac6e3f1a7252b1bbf6bad263bce3d7f99266f</sha1>
  </file>
  <file name="Mario Kart Wii Platinum Soundtrack [MP3]/29. Chain Chomp Wheel.mp3" source="original">
    <mtime>1636284379</mtime>
    <size>5905187</size>
    <md5>c690891505e30ab468538894486b1ad3</md5>
    <crc32>436c1413</crc32>
    <sha1>d43d3090b06a72ab21dcffdd794c2f0ac5f03c71</sha1>
    <format>VBR MP3</format>
    <length>140.23</length>
    <title>Chain Chomp Wheel</title>
    <creator>Asuka Ohta, Ryo Nagamatsu</creator>
    <album>Mario Kart Wii Platinum Soundtrack</album>
    <track>29/43</track>
    <artist>Asuka Ohta, Ryo Nagamatsu</artist>
    <genre>Game Soundtrack</genre>
    <comment>http://sittingonclouds.net</comment>
  </file>
  <file name="Mario Kart Wii Platinum Soundtrack [MP3]/29. Chain Chomp Wheel.png" source="derivative">
    <format>PNG</format>
    <original>Mario Kart Wii Platinum Soundtrack [MP3]/29. Chain Chomp Wheel.mp3</original>
    <mtime>1636287405</mtime>
    <size>43177</size>
    <md5>f1db7fcf7dfb550a344395817f8e2390</md5>
    <crc32>59cbcd33</crc32>
    <sha1>d86b02764c2138205c46ec7103db0b5d28b6bc9e</sha1>
  </file>
  <file name="Mario Kart Wii Platinum Soundtrack [MP3]/29. Chain Chomp Wheel_spectrogram.png" source="derivative">
    <format>Spectrogram</format>
    <original>Mario Kart Wii Platinum Soundtrack [MP3]/29. Chain Chomp Wheel.mp3</original>
    <mtime>1636290557</mtime>
    <size>327718</size>
    <md5>a6ceeb2c5677599f1eb4f0aabd7d33bc</md5>
    <crc32>18520aae</crc32>
    <sha1>94e7bceecb6adc76eb6ab23a207ec8f1236d26b9</sha1>
  </file>
  <file name="Mario Kart Wii Platinum Soundtrack [MP3]/30. Thwomp Desert.afpk" source="derivative">
    <format>Columbia Peaks</format>
    <original>Mario Kart Wii Platinum Soundtrack [MP3]/30. Thwomp Desert.mp3</original>
    <mtime>1636292940</mtime>
    <size>31272</size>
    <md5>4715a6bcf38916c2c0d5ec04a2a8d3a6</md5>
    <crc32>d4c9e328</crc32>
    <sha1>b01f5738ab2d5fb8f350cd3578bd9519e1f78f80</sha1>
  </file>
  <file name="Mario Kart Wii Platinum Soundtrack [MP3]/30. Thwomp Desert.mp3" source="original">
    <mtime>1636284282</mtime>
    <size>5594844</size>
    <md5>3636e6bdd6123ac36e0d6e06188d0fcc</md5>
    <crc32>412ce0b9</crc32>
    <sha1>021b471a97be2c7215a57ff2d2443485256e6584</sha1>
    <format>VBR MP3</format>
    <length>132.47</length>
    <title>Thwomp Desert</title>
    <creator>Asuka Ohta, Ryo Nagamatsu</creator>
    <album>Mario Kart Wii Platinum Soundtrack</album>
    <track>30/43</track>
    <artist>Asuka Ohta, Ryo Nagamatsu</artist>
    <genre>Game Soundtrack</genre>
    <comment>http://sittingonclouds.net</comment>
  </file>
  <file name="Mario Kart Wii Platinum Soundtrack [MP3]/30. Thwomp Desert.png" source="derivative">
    <format>PNG</format>
    <original>Mario Kart Wii Platinum Soundtrack [MP3]/30. Thwomp Desert.mp3</original>
    <mtime>1636285500</mtime>
    <size>43506</size>
    <md5>00e398f8b19816bf3fd622296f90ded9</md5>
    <crc32>c4cf54fe</crc32>
    <sha1>1a0e689d141a400bd4708482cac548c93beefc8e</sha1>
  </file>
  <file name="Mario Kart Wii Platinum Soundtrack [MP3]/30. Thwomp Desert_spectrogram.png" source="derivative">
    <format>Spectrogram</format>
    <original>Mario Kart Wii Platinum Soundtrack [MP3]/30. Thwomp Desert.mp3</original>
    <mtime>1636291208</mtime>
    <size>312615</size>
    <md5>dd4f4fa5e060efcb8dc66bccf8df3d1c</md5>
    <crc32>23af3e37</crc32>
    <sha1>08f60909c8872e769332bc7a2adaee34800bb8e7</sha1>
  </file>
  <file name="Mario Kart Wii Platinum Soundtrack [MP3]/31. 1st Place in Team (Battle) - New Record (Time Trial) Fanfare.afpk" source="derivative">
    <format>Columbia Peaks</format>
    <original>Mario Kart Wii Platinum Soundtrack [MP3]/31. 1st Place in Team (Battle) - New Record (Time Trial) Fanfare.mp3</original>
    <mtime>1636294420</mtime>
    <size>1112</size>
    <md5>2bcd237982fe0957ec9d0277e802acda</md5>
    <crc32>19ed1269</crc32>
    <sha1>d2c8369a9a5fb319f8258fb324490b3f7e782739</sha1>
  </file>
  <file name="Mario Kart Wii Platinum Soundtrack [MP3]/31. 1st Place in Team (Battle) - New Record (Time Trial) Fanfare.mp3" source="original">
    <mtime>1636284291</mtime>
    <size>528228</size>
    <md5>4cbc37540fd019ae1f5fce52ddc8d7b9</md5>
    <crc32>f9e2a6fc</crc32>
    <sha1>146fe66cd3003ca22f81415e15a5eddf17426682</sha1>
    <format>VBR MP3</format>
    <length>5.8</length>
    <title>1st Place in Team (Battle) / New Record (Time Trial) Fanfare</title>
    <creator>Asuka Ohta, Ryo Nagamatsu</creator>
    <album>Mario Kart Wii Platinum Soundtrack</album>
    <track>31/43</track>
    <artist>Asuka Ohta, Ryo Nagamatsu</artist>
    <genre>Game Soundtrack</genre>
    <comment>http://sittingonclouds.net</comment>
  </file>
  <file name="Mario Kart Wii Platinum Soundtrack [MP3]/31. 1st Place in Team (Battle) - New Record (Time Trial) Fanfare.png" source="derivative">
    <format>PNG</format>
    <original>Mario Kart Wii Platinum Soundtrack [MP3]/31. 1st Place in Team (Battle) - New Record (Time Trial) Fanfare.mp3</original>
    <mtime>1636284861</mtime>
    <size>25379</size>
    <md5>004d37f18065574facffbf1dfcea4b63</md5>
    <crc32>3e1080f6</crc32>
    <sha1>ba44cb1cf1d32b38f0a59601a7c64171cae14596</sha1>
  </file>
  <file name="Mario Kart Wii Platinum Soundtrack [MP3]/31. 1st Place in Team (Battle) - New Record (Time Trial) Fanfare_spectrogram.png" source="derivative">
    <format>Spectrogram</format>
    <original>Mario Kart Wii Platinum Soundtrack [MP3]/31. 1st Place in Team (Battle) - New Record (Time Trial) Fanfare.mp3</original>
    <mtime>1636290908</mtime>
    <size>314632</size>
    <md5>35f3663846858129f2ff757c0c42699c</md5>
    <crc32>a2fedd1e</crc32>
    <sha1>94d658a61e7762ad04e00bc7a092239950e2be0e</sha1>
  </file>
  <file name="Mario Kart Wii Platinum Soundtrack [MP3]/32. Team Victory (Battle) - Record (Time Trial) Fanfare.afpk" source="derivative">
    <format>Columbia Peaks</format>
    <original>Mario Kart Wii Platinum Soundtrack [MP3]/32. Team Victory (Battle) - Record (Time Trial) Fanfare.mp3</original>
    <mtime>1636294521</mtime>
    <size>1056</size>
    <md5>007800f70e25d0966540f90eb3fefb30</md5>
    <crc32>8cfcd72c</crc32>
    <sha1>460949dcb60628a3c10193124a93b3c83fbd3349</sha1>
  </file>
  <file name="Mario Kart Wii Platinum Soundtrack [MP3]/32. Team Victory (Battle) - Record (Time Trial) Fanfare.mp3" source="original">
    <mtime>1636284165</mtime>
    <size>531345</size>
    <md5>886ed4e3b7fd6f4ba17d0d4f642a7ef8</md5>
    <crc32>6964ec82</crc32>
    <sha1>95eeff16adc7c87dcb24847b1150a841c9fa8b90</sha1>
    <format>VBR MP3</format>
    <length>5.88</length>
    <title>Team Victory (Battle) / Record (Time Trial) Fanfare</title>
    <creator>Asuka Ohta, Ryo Nagamatsu</creator>
    <album>Mario Kart Wii Platinum Soundtrack</album>
    <track>32/43</track>
    <artist>Asuka Ohta, Ryo Nagamatsu</artist>
    <genre>Game Soundtrack</genre>
    <comment>http://sittingonclouds.net</comment>
  </file>
  <file name="Mario Kart Wii Platinum Soundtrack [MP3]/32. Team Victory (Battle) - Record (Time Trial) Fanfare.png" source="derivative">
    <format>PNG</format>
    <original>Mario Kart Wii Platinum Soundtrack [MP3]/32. Team Victory (Battle) - Record (Time Trial) Fanfare.mp3</original>
    <mtime>1636285191</mtime>
    <size>25363</size>
    <md5>55aa188f21b9ede9e5c4f056d527e069</md5>
    <crc32>c9e9c3d2</crc32>
    <sha1>361833eb045335a062da0e179cf9f07ba7ce464b</sha1>
  </file>
  <file name="Mario Kart Wii Platinum Soundtrack [MP3]/32. Team Victory (Battle) - Record (Time Trial) Fanfare_spectrogram.png" source="derivative">
    <format>Spectrogram</format>
    <original>Mario Kart Wii Platinum Soundtrack [MP3]/32. Team Victory (Battle) - Record (Time Trial) Fanfare.mp3</original>
    <mtime>1636288746</mtime>
    <size>335148</size>
    <md5>707ba744d9fa95237d560c217e36544e</md5>
    <crc32>2f8865b1</crc32>
    <sha1>75147ef056d84c70e56e0a95360a84aad9c90697</sha1>
  </file>
  <file name="Mario Kart Wii Platinum Soundtrack [MP3]/33. Draw Fanfare.afpk" source="derivative">
    <format>Columbia Peaks</format>
    <original>Mario Kart Wii Platinum Soundtrack [MP3]/33. Draw Fanfare.mp3</original>
    <mtime>1636292835</mtime>
    <size>824</size>
    <md5>84c8ed6dee907ffbc6d3888704bea04e</md5>
    <crc32>21f626ad</crc32>
    <sha1>293bbc8a1b01da933f80fb2e880f4ddd77f539ed</sha1>
  </file>
  <file name="Mario Kart Wii Platinum Soundtrack [MP3]/33. Draw Fanfare.mp3" source="original">
    <mtime>1636284329</mtime>
    <size>524997</size>
    <md5>cb247b0b581e4306757965e29eddb2ee</md5>
    <crc32>faf2ca1c</crc32>
    <sha1>5cf291c8e195f3121f2773c9e6b61839363c7014</sha1>
    <format>VBR MP3</format>
    <length>5.72</length>
    <title>Draw Fanfare</title>
    <creator>Asuka Ohta, Ryo Nagamatsu</creator>
    <album>Mario Kart Wii Platinum Soundtrack</album>
    <track>33/43</track>
    <artist>Asuka Ohta, Ryo Nagamatsu</artist>
    <genre>Game Soundtrack</genre>
    <comment>http://sittingonclouds.net</comment>
  </file>
  <file name="Mario Kart Wii Platinum Soundtrack [MP3]/33. Draw Fanfare.png" source="derivative">
    <format>PNG</format>
    <original>Mario Kart Wii Platinum Soundtrack [MP3]/33. Draw Fanfare.mp3</original>
    <mtime>1636285255</mtime>
    <size>20026</size>
    <md5>8de78f87ebb8129c5630247902727fa0</md5>
    <crc32>00887764</crc32>
    <sha1>b6a5ec1267086b92516c2683c5f44ae186cec800</sha1>
  </file>
  <file name="Mario Kart Wii Platinum Soundtrack [MP3]/33. Draw Fanfare_spectrogram.png" source="derivative">
    <format>Spectrogram</format>
    <original>Mario Kart Wii Platinum Soundtrack [MP3]/33. Draw Fanfare.mp3</original>
    <mtime>1636290177</mtime>
    <size>322934</size>
    <md5>251349e04dc356ddcb86570a76807d9a</md5>
    <crc32>43c2cae6</crc32>
    <sha1>1d6cbda0a1124d754092556421a0a230cd73ba02</sha1>
  </file>
  <file name="Mario Kart Wii Platinum Soundtrack [MP3]/34. Team Victory (Battle) - Record (Time Trial) Results.afpk" source="derivative">
    <format>Columbia Peaks</format>
    <original>Mario Kart Wii Platinum Soundtrack [MP3]/34. Team Victory (Battle) - Record (Time Trial) Results.mp3</original>
    <mtime>1636293823</mtime>
    <size>6400</size>
    <md5>c0ae548c21e171bf6e3276ae8287339d</md5>
    <crc32>13272308</crc32>
    <sha1>60fb0e9a44299aa4dda5f397fa081b2afa9036a0</sha1>
  </file>
  <file name="Mario Kart Wii Platinum Soundtrack [MP3]/34. Team Victory (Battle) - Record (Time Trial) Results.mp3" source="original">
    <mtime>1636284358</mtime>
    <size>1359949</size>
    <md5>5de4dc63408c1d4e34936872944b3cc5</md5>
    <crc32>6a3a3622</crc32>
    <sha1>1f1c7a54aedf12d9142b5d194b3b33e46102ea9d</sha1>
    <format>VBR MP3</format>
    <length>26.59</length>
    <title>Team Victory (Battle) / Record (Time Trial) Results</title>
    <creator>Asuka Ohta, Ryo Nagamatsu</creator>
    <album>Mario Kart Wii Platinum Soundtrack</album>
    <track>34/43</track>
    <artist>Asuka Ohta, Ryo Nagamatsu</artist>
    <genre>Game Soundtrack</genre>
    <comment>http://sittingonclouds.net</comment>
  </file>
  <file name="Mario Kart Wii Platinum Soundtrack [MP3]/34. Team Victory (Battle) - Record (Time Trial) Results.png" source="derivative">
    <format>PNG</format>
    <original>Mario Kart Wii Platinum Soundtrack [MP3]/34. Team Victory (Battle) - Record (Time Trial) Results.mp3</original>
    <mtime>1636285342</mtime>
    <size>32885</size>
    <md5>71bea6024ce372e67c9939b241d2ad92</md5>
    <crc32>33135feb</crc32>
    <sha1>bc86c296027325d348a79d6aa88b5b270e8863fa</sha1>
  </file>
  <file name="Mario Kart Wii Platinum Soundtrack [MP3]/34. Team Victory (Battle) - Record (Time Trial) Results_spectrogram.png" source="derivative">
    <format>Spectrogram</format>
    <original>Mario Kart Wii Platinum Soundtrack [MP3]/34. Team Victory (Battle) - Record (Time Trial) Results.mp3</original>
    <mtime>1636289508</mtime>
    <size>347644</size>
    <md5>64710f89a0cbc341998d910f258a8ead</md5>
    <crc32>126cf385</crc32>
    <sha1>2db7c0dea6b87a45325e5411321ffffa6312456e</sha1>
  </file>
  <file name="Mario Kart Wii Platinum Soundtrack [MP3]/35. Team Defeat (Battle) - No Record (Time Trial) Fanfare.afpk" source="derivative">
    <format>Columbia Peaks</format>
    <original>Mario Kart Wii Platinum Soundtrack [MP3]/35. Team Defeat (Battle) - No Record (Time Trial) Fanfare.mp3</original>
    <mtime>1636294720</mtime>
    <size>1360</size>
    <md5>33971a0b8786a26a2664b3432dd2e6b8</md5>
    <crc32>e4bd7075</crc32>
    <sha1>4b6a2717adb06e5d4c091813ff0e0f79d9bad34f</sha1>
  </file>
  <file name="Mario Kart Wii Platinum Soundtrack [MP3]/35. Team Defeat (Battle) - No Record (Time Trial) Fanfare.mp3" source="original">
    <mtime>1636284239</mtime>
    <size>555381</size>
    <md5>54c012dfa46143cfc2160f85f24d7839</md5>
    <crc32>7e4a2e3a</crc32>
    <sha1>2b1210373a146b59d823ce82a9cc587ef3de0fa8</sha1>
    <format>VBR MP3</format>
    <length>6.48</length>
    <title>Team Defeat (Battle) / No Record (Time Trial) Fanfare</title>
    <creator>Asuka Ohta, Ryo Nagamatsu</creator>
    <album>Mario Kart Wii Platinum Soundtrack</album>
    <track>35/43</track>
    <artist>Asuka Ohta, Ryo Nagamatsu</artist>
    <genre>Game Soundtrack</genre>
    <comment>http://sittingonclouds.net</comment>
  </file>
  <file name="Mario Kart Wii Platinum Soundtrack [MP3]/35. Team Defeat (Battle) - No Record (Time Trial) Fanfare.png" source="derivative">
    <format>PNG</format>
    <original>Mario Kart Wii Platinum Soundtrack [MP3]/35. Team Defeat (Battle) - No Record (Time Trial) Fanfare.mp3</original>
    <mtime>1636285134</mtime>
    <size>25364</size>
    <md5>f57c19dbbba1ed8be6be551c76e5aba0</md5>
    <crc32>ee930fcf</crc32>
    <sha1>73a89c1e34c11ca838fd58321fcd49cbdf89638c</sha1>
  </file>
  <file name="Mario Kart Wii Platinum Soundtrack [MP3]/35. Team Defeat (Battle) - No Record (Time Trial) Fanfare_spectrogram.png" source="derivative">
    <format>Spectrogram</format>
    <original>Mario Kart Wii Platinum Soundtrack [MP3]/35. Team Defeat (Battle) - No Record (Time Trial) Fanfare.mp3</original>
    <mtime>1636289815</mtime>
    <size>344045</size>
    <md5>3c8996b152af6bb7e5b61bb142f91a21</md5>
    <crc32>90bfedcc</crc32>
    <sha1>8ab64a70b405cab7ff24f59e9ffd6fe1c7a868a1</sha1>
  </file>
  <file name="Mario Kart Wii Platinum Soundtrack [MP3]/36. Team Defeat (Battle) - No Record (Time Trial) Results.afpk" source="derivative">
    <format>Columbia Peaks</format>
    <original>Mario Kart Wii Platinum Soundtrack [MP3]/36. Team Defeat (Battle) - No Record (Time Trial) Results.mp3</original>
    <mtime>1636295399</mtime>
    <size>9616</size>
    <md5>c1fe4b7261999656fc0e31eed7d12e25</md5>
    <crc32>e97347f4</crc32>
    <sha1>4bea7d4b004b35a0c817473ce07aad46690d00c1</sha1>
  </file>
  <file name="Mario Kart Wii Platinum Soundtrack [MP3]/36. Team Defeat (Battle) - No Record (Time Trial) Results.mp3" source="original">
    <mtime>1636284355</mtime>
    <size>2235577</size>
    <md5>05e6871994c764edc52e7b6c5e1c12f0</md5>
    <crc32>5a63d521</crc32>
    <sha1>dd99a6fa8710ab2a5ae8b3cc7656f725d9e27fbf</sha1>
    <format>VBR MP3</format>
    <length>48.48</length>
    <title>Team Defeat (Battle) / No Record (Time Trial) Results</title>
    <creator>Asuka Ohta, Ryo Nagamatsu</creator>
    <album>Mario Kart Wii Platinum Soundtrack</album>
    <track>36/43</track>
    <artist>Asuka Ohta, Ryo Nagamatsu</artist>
    <genre>Game Soundtrack</genre>
    <comment>http://sittingonclouds.net</comment>
  </file>
  <file name="Mario Kart Wii Platinum Soundtrack [MP3]/36. Team Defeat (Battle) - No Record (Time Trial) Results.png" source="derivative">
    <format>PNG</format>
    <original>Mario Kart Wii Platinum Soundtrack [MP3]/36. Team Defeat (Battle) - No Record (Time Trial) Results.mp3</original>
    <mtime>1636287984</mtime>
    <size>31276</size>
    <md5>0eaf5fde2ae0a21f4bbad3f9e5b1a1d9</md5>
    <crc32>907819b2</crc32>
    <sha1>0056c0e0d5d11c16ef28a7d9285be7c64a40704b</sha1>
  </file>
  <file name="Mario Kart Wii Platinum Soundtrack [MP3]/36. Team Defeat (Battle) - No Record (Time Trial) Results_spectrogram.png" source="derivative">
    <format>Spectrogram</format>
    <original>Mario Kart Wii Platinum Soundtrack [MP3]/36. Team Defeat (Battle) - No Record (Time Trial) Results.mp3</original>
    <mtime>1636289701</mtime>
    <size>347126</size>
    <md5>67df2eded3cb32f30ce4ca81877c9af0</md5>
    <crc32>02512cdd</crc32>
    <sha1>5885add5f1fad1fcfbd125dd359fae40d02bd221</sha1>
  </file>
  <file name="Mario Kart Wii Platinum Soundtrack [MP3]/37. Mario Kart Channel Menu.afpk" source="derivative">
    <format>Columbia Peaks</format>
    <original>Mario Kart Wii Platinum Soundtrack [MP3]/37. Mario Kart Channel Menu.mp3</original>
    <mtime>1636295255</mtime>
    <size>8192</size>
    <md5>49df3ed6f4f11dca5a06aaf5d3a40382</md5>
    <crc32>22b46c6f</crc32>
    <sha1>b169f53275b661ec60d904d447551c0a88bce70b</sha1>
  </file>
  <file name="Mario Kart Wii Platinum Soundtrack [MP3]/37. Mario Kart Channel Menu.mp3" source="original">
    <mtime>1636284324</mtime>
    <size>2168644</size>
    <md5>0e8d96dd5a6dec74573a5aaf2f5d39b4</md5>
    <crc32>3ece691f</crc32>
    <sha1>ee1cd26f969c94ced72c7bd9884b1ef0c5082dc6</sha1>
    <format>VBR MP3</format>
    <length>46.81</length>
    <title>Mario Kart Channel Menu</title>
    <creator>Asuka Ohta, Ryo Nagamatsu</creator>
    <album>Mario Kart Wii Platinum Soundtrack</album>
    <track>37/43</track>
    <artist>Asuka Ohta, Ryo Nagamatsu</artist>
    <genre>Game Soundtrack</genre>
    <comment>http://sittingonclouds.net</comment>
  </file>
  <file name="Mario Kart Wii Platinum Soundtrack [MP3]/37. Mario Kart Channel Menu.png" source="derivative">
    <format>PNG</format>
    <original>Mario Kart Wii Platinum Soundtrack [MP3]/37. Mario Kart Channel Menu.mp3</original>
    <mtime>1636286756</mtime>
    <size>36647</size>
    <md5>1dba1a15e4638ce26e4afd05ae2141f8</md5>
    <crc32>cc410cb0</crc32>
    <sha1>478d2028cd7a36d57ccbeb3d84b42dd6e3c85813</sha1>
  </file>
  <file name="Mario Kart Wii Platinum Soundtrack [MP3]/37. Mario Kart Channel Menu_spectrogram.png" source="derivative">
    <format>Spectrogram</format>
    <original>Mario Kart Wii Platinum Soundtrack [MP3]/37. Mario Kart Channel Menu.mp3</original>
    <mtime>1636288942</mtime>
    <size>326461</size>
    <md5>7b6fe40fdd2cb7f1115191ab1a81216a</md5>
    <crc32>0e1c143f</crc32>
    <sha1>6ab44ac2a67f035da23364c965e9ba21b584c59c</sha1>
  </file>
  <file name="Mario Kart Wii Platinum Soundtrack [MP3]/38. Records.afpk" source="derivative">
    <format>Columbia Peaks</format>
    <original>Mario Kart Wii Platinum Soundtrack [MP3]/38. Records.mp3</original>
    <mtime>1636292609</mtime>
    <size>12568</size>
    <md5>548af05a5f7fbf9e95d182f7b9272d36</md5>
    <crc32>fd164252</crc32>
    <sha1>644061f234a02185348350b8ae3a542783f0ef39</sha1>
  </file>
  <file name="Mario Kart Wii Platinum Soundtrack [MP3]/38. Records.mp3" source="original">
    <mtime>1636284395</mtime>
    <size>2701510</size>
    <md5>51450025e0af2010c9b7cd7c4c6c6a43</md5>
    <crc32>a9220fdf</crc32>
    <sha1>025900c734ce34b0f2238eb26cbc2c8c3d5e04d1</sha1>
    <format>VBR MP3</format>
    <length>60.13</length>
    <title>Records</title>
    <creator>Asuka Ohta, Ryo Nagamatsu</creator>
    <album>Mario Kart Wii Platinum Soundtrack</album>
    <track>38/43</track>
    <artist>Asuka Ohta, Ryo Nagamatsu</artist>
    <genre>Game Soundtrack</genre>
    <comment>http://sittingonclouds.net</comment>
  </file>
  <file name="Mario Kart Wii Platinum Soundtrack [MP3]/38. Records.png" source="derivative">
    <format>PNG</format>
    <original>Mario Kart Wii Platinum Soundtrack [MP3]/38. Records.mp3</original>
    <mtime>1636285977</mtime>
    <size>31546</size>
    <md5>38c546d71ea73988f167d1286b489ffa</md5>
    <crc32>9364c74f</crc32>
    <sha1>38b453afb28d733416af90a8e497f44b43489551</sha1>
  </file>
  <file name="Mario Kart Wii Platinum Soundtrack [MP3]/38. Records_spectrogram.png" source="derivative">
    <format>Spectrogram</format>
    <original>Mario Kart Wii Platinum Soundtrack [MP3]/38. Records.mp3</original>
    <mtime>1636289119</mtime>
    <size>343043</size>
    <md5>7a135860cc697403c4c2445531bef1ab</md5>
    <crc32>da99ddd6</crc32>
    <sha1>c6e5977de5b9040ebb8e9ae64f12d394e171540f</sha1>
  </file>
  <file name="Mario Kart Wii Platinum Soundtrack [MP3]/39. Wi-Fi Menu.afpk" source="derivative">
    <format>Columbia Peaks</format>
    <original>Mario Kart Wii Platinum Soundtrack [MP3]/39. Wi-Fi Menu.mp3</original>
    <mtime>1636295046</mtime>
    <size>25744</size>
    <md5>5164d29327ba876e4043e0e01c609319</md5>
    <crc32>e050d060</crc32>
    <sha1>b80ac9e7b640540171a289978b947cbc253de3dc</sha1>
  </file>
  <file name="Mario Kart Wii Platinum Soundtrack [MP3]/39. Wi-Fi Menu.mp3" source="original">
    <mtime>1636284257</mtime>
    <size>6583312</size>
    <md5>f4f4daa137a53ef7aa585bee653898b4</md5>
    <crc32>17181c27</crc32>
    <sha1>c68eaa1417fd13d25c751b8a203d3cb2fa22a4ea</sha1>
    <format>VBR MP3</format>
    <length>157.18</length>
    <title>Wi-Fi Menu</title>
    <creator>Asuka Ohta, Ryo Nagamatsu</creator>
    <album>Mario Kart Wii Platinum Soundtrack</album>
    <track>39/43</track>
    <artist>Asuka Ohta, Ryo Nagamatsu</artist>
    <genre>Game Soundtrack</genre>
    <comment>http://sittingonclouds.net</comment>
  </file>
  <file name="Mario Kart Wii Platinum Soundtrack [MP3]/39. Wi-Fi Menu.png" source="derivative">
    <format>PNG</format>
    <original>Mario Kart Wii Platinum Soundtrack [MP3]/39. Wi-Fi Menu.mp3</original>
    <mtime>1636286891</mtime>
    <size>37602</size>
    <md5>d63173b37ac945a630d4ee687c0db31b</md5>
    <crc32>61704bbc</crc32>
    <sha1>d0971f88893fd50e85f0df64640fb19a5a997fb5</sha1>
  </file>
  <file name="Mario Kart Wii Platinum Soundtrack [MP3]/39. Wi-Fi Menu_spectrogram.png" source="derivative">
    <format>Spectrogram</format>
    <original>Mario Kart Wii Platinum Soundtrack [MP3]/39. Wi-Fi Menu.mp3</original>
    <mtime>1636292157</mtime>
    <size>323979</size>
    <md5>59c968db673306d95b0e07b753dec9f2</md5>
    <crc32>b070340d</crc32>
    <sha1>ff0b1637df87dfc661f320375f9a278f0c1e3ede</sha1>
  </file>
  <file name="Mario Kart Wii Platinum Soundtrack [MP3]/40. Wi-Fi Match-Ghost Replay.afpk" source="derivative">
    <format>Columbia Peaks</format>
    <original>Mario Kart Wii Platinum Soundtrack [MP3]/40. Wi-Fi Match-Ghost Replay.mp3</original>
    <mtime>1636292766</mtime>
    <size>10080</size>
    <md5>558a16d86b0b3b3f5020924320a559db</md5>
    <crc32>3e5d618d</crc32>
    <sha1>6c4ce9e9ddfc330b03c61053d0bdb30564391e94</sha1>
  </file>
  <file name="Mario Kart Wii Platinum Soundtrack [MP3]/40. Wi-Fi Match-Ghost Replay.mp3" source="original">
    <mtime>1636284321</mtime>
    <size>2476891</size>
    <md5>fcd50f193630c5c8734f03fdb9d280f3</md5>
    <crc32>0eac9bd0</crc32>
    <sha1>d972a3a70748e29eae1994190df81fe77315a47a</sha1>
    <format>VBR MP3</format>
    <length>54.52</length>
    <title>Wi-Fi Match/Ghost Replay</title>
    <creator>Asuka Ohta, Ryo Nagamatsu</creator>
    <album>Mario Kart Wii Platinum Soundtrack</album>
    <track>40/43</track>
    <artist>Asuka Ohta, Ryo Nagamatsu</artist>
    <genre>Game Soundtrack</genre>
    <comment>http://sittingonclouds.net</comment>
  </file>
  <file name="Mario Kart Wii Platinum Soundtrack [MP3]/40. Wi-Fi Match-Ghost Replay.png" source="derivative">
    <format>PNG</format>
    <original>Mario Kart Wii Platinum Soundtrack [MP3]/40. Wi-Fi Match-Ghost Replay.mp3</original>
    <mtime>1636288126</mtime>
    <size>37910</size>
    <md5>c4dcf4aa4b57f8da276fe8b953bb4557</md5>
    <crc32>3e494983</crc32>
    <sha1>3e973a4458cdcae80209f1e40ac3c77085f96501</sha1>
  </file>
  <file name="Mario Kart Wii Platinum Soundtrack [MP3]/40. Wi-Fi Match-Ghost Replay_spectrogram.png" source="derivative">
    <format>Spectrogram</format>
    <original>Mario Kart Wii Platinum Soundtrack [MP3]/40. Wi-Fi Match-Ghost Replay.mp3</original>
    <mtime>1636289981</mtime>
    <size>350037</size>
    <md5>edd5a5bd05f435453f9ef67da03f9787</md5>
    <crc32>9f703af3</crc32>
    <sha1>e6468e0ec804eda45b9c8a85c9d613134ecb63c3</sha1>
  </file>
  <file name="Mario Kart Wii Platinum Soundtrack [MP3]/41. Award Ceremony.afpk" source="derivative">
    <format>Columbia Peaks</format>
    <original>Mario Kart Wii Platinum Soundtrack [MP3]/41. Award Ceremony.mp3</original>
    <mtime>1636296147</mtime>
    <size>19504</size>
    <md5>b4682c409409514319101ebf16c39867</md5>
    <crc32>05366118</crc32>
    <sha1>52d8bcaaa7580d4c871a5a5f91762601fc803cfa</sha1>
  </file>
  <file name="Mario Kart Wii Platinum Soundtrack [MP3]/41. Award Ceremony.mp3" source="original">
    <mtime>1636284200</mtime>
    <size>3817475</size>
    <md5>b53d7ed0149108a606eabe2997f8454e</md5>
    <crc32>a8a80add</crc32>
    <sha1>1f8d3cd679b4e411d696dde40527447507a154a3</sha1>
    <format>VBR MP3</format>
    <length>88.03</length>
    <title>Award Ceremony</title>
    <creator>Asuka Ohta, Ryo Nagamatsu</creator>
    <album>Mario Kart Wii Platinum Soundtrack</album>
    <track>41/43</track>
    <artist>Asuka Ohta, Ryo Nagamatsu</artist>
    <genre>Game Soundtrack</genre>
    <comment>http://sittingonclouds.net</comment>
  </file>
  <file name="Mario Kart Wii Platinum Soundtrack [MP3]/41. Award Ceremony.png" source="derivative">
    <format>PNG</format>
    <original>Mario Kart Wii Platinum Soundtrack [MP3]/41. Award Ceremony.mp3</original>
    <mtime>1636287883</mtime>
    <size>42004</size>
    <md5>17512127d96195c82696d19e7627815b</md5>
    <crc32>63a9c570</crc32>
    <sha1>df22ae4ea581b9f1694728f61b8050d39c6c8275</sha1>
  </file>
  <file name="Mario Kart Wii Platinum Soundtrack [MP3]/41. Award Ceremony_spectrogram.png" source="derivative">
    <format>Spectrogram</format>
    <original>Mario Kart Wii Platinum Soundtrack [MP3]/41. Award Ceremony.mp3</original>
    <mtime>1636289386</mtime>
    <size>333814</size>
    <md5>cadc4b8a0d34a97fc812c2ba12431726</md5>
    <crc32>648c58b8</crc32>
    <sha1>1561f5e3e980b4068f0aed2bc553344007b06f5e</sha1>
  </file>
  <file name="Mario Kart Wii Platinum Soundtrack [MP3]/42. Staff Credits A.afpk" source="derivative">
    <format>Columbia Peaks</format>
    <original>Mario Kart Wii Platinum Soundtrack [MP3]/42. Staff Credits A.mp3</original>
    <mtime>1636294279</mtime>
    <size>20904</size>
    <md5>564a9c328d5b490a8eb06ec958f4e95d</md5>
    <crc32>ecf4b57e</crc32>
    <sha1>13d7038f27b30759024ccc76322240bfce14d517</sha1>
  </file>
  <file name="Mario Kart Wii Platinum Soundtrack [MP3]/42. Staff Credits A.mp3" source="original">
    <mtime>1636284226</mtime>
    <size>4608464</size>
    <md5>8bf184de34e655912028ad130242b38d</md5>
    <crc32>d31c9bfc</crc32>
    <sha1>fa5d76a91ef3228df93927ba9567dc294a09531b</sha1>
    <format>VBR MP3</format>
    <length>107.81</length>
    <title>Staff Credits A</title>
    <creator>Asuka Ohta, Ryo Nagamatsu</creator>
    <album>Mario Kart Wii Platinum Soundtrack</album>
    <track>42/43</track>
    <artist>Asuka Ohta, Ryo Nagamatsu</artist>
    <genre>Game Soundtrack</genre>
    <comment>http://sittingonclouds.net</comment>
  </file>
  <file name="Mario Kart Wii Platinum Soundtrack [MP3]/42. Staff Credits A.png" source="derivative">
    <format>PNG</format>
    <original>Mario Kart Wii Platinum Soundtrack [MP3]/42. Staff Credits A.mp3</original>
    <mtime>1636287554</mtime>
    <size>35722</size>
    <md5>930b147137a3606df0600c5e004bc8c1</md5>
    <crc32>299b0813</crc32>
    <sha1>5d7874bc4f8d8be5226f91bae4ff49272df87755</sha1>
  </file>
  <file name="Mario Kart Wii Platinum Soundtrack [MP3]/42. Staff Credits A_spectrogram.png" source="derivative">
    <format>Spectrogram</format>
    <original>Mario Kart Wii Platinum Soundtrack [MP3]/42. Staff Credits A.mp3</original>
    <mtime>1636289212</mtime>
    <size>325952</size>
    <md5>3b2dbfc2eb8a97df09df44c183500fbb</md5>
    <crc32>8623ce99</crc32>
    <sha1>613a84599c2c4409f7dd7f8458c52ac4a992b1ac</sha1>
  </file>
  <file name="Mario Kart Wii Platinum Soundtrack [MP3]/43. Staff Credits B.afpk" source="derivative">
    <format>Columbia Peaks</format>
    <original>Mario Kart Wii Platinum Soundtrack [MP3]/43. Staff Credits B.mp3</original>
    <mtime>1636294804</mtime>
    <size>26888</size>
    <md5>0971e53c67d91f6b905b6fd1479ee22a</md5>
    <crc32>da764a89</crc32>
    <sha1>96073a7eb7bc28422377394ce2cbe648947c794c</sha1>
  </file>
  <file name="Mario Kart Wii Platinum Soundtrack [MP3]/43. Staff Credits B.mp3" source="original">
    <mtime>1636284140</mtime>
    <size>5879060</size>
    <md5>0c1cb8af98fb9a76036fe084ce7196fd</md5>
    <crc32>4590d615</crc32>
    <sha1>c049040cc286e198135863b0dbbb2bb479a9ef5a</sha1>
    <format>VBR MP3</format>
    <length>139.57</length>
    <title>Staff Credits B</title>
    <creator>Asuka Ohta, Ryo Nagamatsu</creator>
    <album>Mario Kart Wii Platinum Soundtrack</album>
    <track>43/43</track>
    <artist>Asuka Ohta, Ryo Nagamatsu</artist>
    <genre>Game Soundtrack</genre>
    <comment>http://sittingonclouds.net</comment>
  </file>
  <file name="Mario Kart Wii Platinum Soundtrack [MP3]/43. Staff Credits B.png" source="derivative">
    <format>PNG</format>
    <original>Mario Kart Wii Platinum Soundtrack [MP3]/43. Staff Credits B.mp3</original>
    <mtime>1636286292</mtime>
    <size>41853</size>
    <md5>68b07530497c4cf91d05c8f48450c8d9</md5>
    <crc32>61e32a7e</crc32>
    <sha1>a019569a393d59e89bdae410d8589dbd13862976</sha1>
  </file>
  <file name="Mario Kart Wii Platinum Soundtrack [MP3]/43. Staff Credits B_spectrogram.png" source="derivative">
    <format>Spectrogram</format>
    <original>Mario Kart Wii Platinum Soundtrack [MP3]/43. Staff Credits B.mp3</original>
    <mtime>1636289590</mtime>
    <size>324147</size>
    <md5>4a223e46774b6db17218d952e455ec73</md5>
    <crc32>ad1344ca</crc32>
    <sha1>41c086b0646f7de920646d36a30166d36ca9dea8</sha1>
  </file>
  <file name="Mario Kart Wii Platinum Soundtrack [MP3]/Cover.jpg" source="original">
    <mtime>1636284326</mtime>
    <size>223319</size>
    <md5>e848ca308dd6bdb5b31090cff93e0cf7</md5>
    <crc32>ae4ed95d</crc32>
    <sha1>27a31a8adf02dfc954de4e02f61cf3a755b12b94</sha1>
    <format>JPEG</format>
    <rotation>0</rotation>
  </file>
  <file name="__ia_thumb.jpg" source="original">
    <mtime>1636296757</mtime>
    <size>15063</size>
    <md5>e249b30fb910232cb9874f481b0edcd6</md5>
    <crc32>2b19a812</crc32>
    <sha1>0a015394f54e2903ea83ce8faf14142d6e925093</sha1>
    <format>Item Tile</format>
    <rotation>0</rotation>
  </file>
  <file name="img002.png" source="original">
    <mtime>1636284418</mtime>
    <size>8683822</size>
    <md5>b4bde8a45f66a031fcf49d196957c6f4</md5>
    <crc32>9005396d</crc32>
    <sha1>33463409eebd37625897b3f5eae2c709044359d2</sha1>
    <format>PNG</format>
  </file>
  <file name="img002_thumb.jpg" source="derivative">
    <format>JPEG Thumb</format>
    <original>img002.png</original>
    <mtime>1636284793</mtime>
    <size>8468</size>
    <md5>270e9068edf78e5d53717dd802a765f5</md5>
    <crc32>8ad1d275</crc32>
    <sha1>5ad3b993636c9ced91cbc4d7eaec3003270e34bc</sha1>
  </file>
  <file name="img003.png" source="original">
    <mtime>1636284426</mtime>
    <size>9820123</size>
    <md5>4f0102d9f7caea066968731956128561</md5>
    <crc32>3ada3b4e</crc32>
    <sha1>bbd7fb9fdc6e15e1e1bc57b00f9893f42ade1f7c</sha1>
    <format>PNG</format>
  </file>
  <file name="img003_thumb.jpg" source="derivative">
    <format>JPEG Thumb</format>
    <original>img003.png</original>
    <mtime>1636284781</mtime>
    <size>11975</size>
    <md5>fbe579ed0ebaa4b9972c1dffa9f16b4e</md5>
    <crc32>f3632a06</crc32>
    <sha1>0d2ba0838997d3d2ab339db3ecf778b67c53b227</sha1>
  </file>
  <file name="img004.png" source="original">
    <mtime>1636284436</mtime>
    <size>14697495</size>
    <md5>69ca64569555ae53ec95cc8ca64d2915</md5>
    <crc32>b0dd580a</crc32>
    <sha1>96f399fd4b340c766af9bcf8522600d1d5f06b50</sha1>
    <format>PNG</format>
  </file>
  <file name="img004_thumb.jpg" source="derivative">
    <format>JPEG Thumb</format>
    <original>img004.png</original>
    <mtime>1636284754</mtime>
    <size>10835</size>
    <md5>a99b1af759ac122e1c5e5d574130b0de</md5>
    <crc32>80c6fb12</crc32>
    <sha1>2ffc56122fc13da4513cb24fa57b97bfdc7d1406</sha1>
  </file>
  <file name="img005.png" source="original">
    <mtime>1636284443</mtime>
    <size>14095703</size>
    <md5>f9704346cbd6f32ff14ef43e1f54b42b</md5>
    <crc32>d7ec7d42</crc32>
    <sha1>a561d744415e8c90906aa67a4b046fc7d7c84ecc</sha1>
    <format>PNG</format>
  </file>
  <file name="img005_thumb.jpg" source="derivative">
    <format>JPEG Thumb</format>
    <original>img005.png</original>
    <mtime>1636284763</mtime>
    <size>10982</size>
    <md5>d012c45d002ea8776c60b7a6fe88e2cd</md5>
    <crc32>a7bd7584</crc32>
    <sha1>8b8da9e9dd481381546946f17d78ef3b84c83c02</sha1>
  </file>
  <file name="img006.png" source="original">
    <mtime>1636284447</mtime>
    <size>5123328</size>
    <md5>77376c2c1468a17a5187fe80843f7c47</md5>
    <crc32>529e45a3</crc32>
    <sha1>4777d3dee4c7cd19253417ac19666a8519549fe5</sha1>
    <format>PNG</format>
  </file>
  <file name="img006_thumb.jpg" source="derivative">
    <format>JPEG Thumb</format>
    <original>img006.png</original>
    <mtime>1636284770</mtime>
    <size>9857</size>
    <md5>e70d89cc5bf72101de4e54fd755623a4</md5>
    <crc32>22137964</crc32>
    <sha1>28ab8ca13b0f79c8b00b05b2b32719a7ef5ebf1e</sha1>
  </file>
</files>
