<?xml version="1.0" encoding="UTF-8"?>
<metadata>
  <identifier>star-trek-6</identifier>
  <mediatype>audio</mediatype>
  <collection>hifidelity_soundtracks</collection>
  <creator>MUNDO ESTELAR</creator>
  <description>Cortesía MUNDO ESTELAR&lt;br /&gt;</description>
  <scanner>Internet Archive HTML5 Uploader 1.6.4</scanner>
  <subject>STAR TREK</subject>
  <subject>SOUNDTRACK</subject>
  <subject>FILMS</subject>
  <subject>SPOCK</subject>
  <subject>KIRK</subject>
  <subject>ENTERPRISE</subject>
  <title>STAR TREK VI: THE UNDISCOVERED COUNTRY – OST 1991</title>
  <uploader>arielmontero1553@gmail.com</uploader>
  <publicdate>2020-11-04 04:12:51</publicdate>
  <addeddate>2020-11-04 04:12:51</addeddate>
  <curation>[curator]validator@archive.org[/curator][date]20201104041314[/date][comment]checked for malware[/comment]</curation>
  <collection>hifidelity</collection>
</metadata>
